[
  {
    "id": "bd-src",
    "title": "মাই টিভি",
    "url": "https://mytvbd.tv/feed",
    "kind": "news",
    "topic": "world",
    "lean": null,
    "confidence": 0.4,
    "leanRationale": "Discovered via dataset; lean assigned per item by analysis (not source-level).",
    "lang": "bn",
    "region": "BD-C",
    "regionLabel": "ঢাকা বিভাগ"
  },
  {
    "id": "bd-src-2",
    "title": "দৈনিক প্রথম আলো",
    "url": "http://www.prothomalo.com/feed",
    "kind": "news",
    "topic": "world",
    "lean": null,
    "confidence": 0.4,
    "leanRationale": "Discovered via dataset; lean assigned per item by analysis (not source-level).",
    "lang": "bn",
    "region": "BD-C",
    "regionLabel": "ঢাকা বিভাগ"
  },
  {
    "id": "bd-src-3",
    "title": "এশিয়ান টিভি",
    "url": "https://www.asiantvonline.com/rss-feed.xml",
    "kind": "news",
    "topic": "world",
    "lean": null,
    "confidence": 0.4,
    "leanRationale": "Discovered via dataset; lean assigned per item by analysis (not source-level).",
    "lang": "bn",
    "region": "BD-C",
    "regionLabel": "ঢাকা বিভাগ"
  },
  {
    "id": "bd-src-4",
    "title": "দৈনিক আমার দেশ",
    "url": "https://dailyamardesh.com/feed",
    "kind": "news",
    "topic": "world",
    "lean": null,
    "confidence": 0.4,
    "leanRationale": "Discovered via dataset; lean assigned per item by analysis (not source-level).",
    "lang": "bn"
  },
  {
    "id": "bd-src-5",
    "title": "চ্যানেল নাইন",
    "url": "https://www.channelninebd.tv/feed/",
    "kind": "news",
    "topic": "world",
    "lean": null,
    "confidence": 0.4,
    "leanRationale": "Discovered via dataset; lean assigned per item by analysis (not source-level).",
    "lang": "bn",
    "region": "BD-C",
    "regionLabel": "ঢাকা বিভাগ"
  },
  {
    "id": "bd-src-6",
    "title": "চ্যানেল আই",
    "url": "https://www.channelionline.com/feed/",
    "kind": "news",
    "topic": "world",
    "lean": null,
    "confidence": 0.4,
    "leanRationale": "Discovered via dataset; lean assigned per item by analysis (not source-level).",
    "lang": "bn",
    "region": "BD-C",
    "regionLabel": "ঢাকা বিভাগ"
  },
  {
    "id": "bd-src-7",
    "title": "জিটিভি",
    "url": "https://gazitv.com/feed/",
    "kind": "news",
    "topic": "world",
    "lean": null,
    "confidence": 0.4,
    "leanRationale": "Discovered via dataset; lean assigned per item by analysis (not source-level).",
    "lang": "bn"
  },
  {
    "id": "bd-src-8",
    "title": "দৈনিক সুপ্রভাত বাংলাদেশ",
    "url": "https://suprobhat.com/feed/",
    "kind": "news",
    "topic": "world",
    "lean": null,
    "confidence": 0.4,
    "leanRationale": "Discovered via dataset; lean assigned per item by analysis (not source-level).",
    "lang": "bn"
  },
  {
    "id": "bd-src-9",
    "title": "দৈনিক পূর্বকোণ",
    "url": "http://www.dainikpurbokone.net/feed",
    "kind": "news",
    "topic": "world",
    "lean": null,
    "confidence": 0.4,
    "leanRationale": "Discovered via dataset; lean assigned per item by analysis (not source-level).",
    "lang": "bn",
    "region": "BD-B",
    "regionLabel": "চট্টগ্রাম বিভাগ"
  },
  {
    "id": "bd-src-10",
    "title": "বাংলা ট্রিবিউন",
    "url": "http://www.banglatribune.com/feed/",
    "kind": "news",
    "topic": "world",
    "lean": null,
    "confidence": 0.4,
    "leanRationale": "Discovered via dataset; lean assigned per item by analysis (not source-level).",
    "lang": "bn",
    "region": "BD-C",
    "regionLabel": "ঢাকা বিভাগ"
  },
  {
    "id": "bd-src-11",
    "title": "শীর্ষনিউজ ডট কম",
    "url": "https://sheershanews.com/feed",
    "kind": "news",
    "topic": "world",
    "lean": null,
    "confidence": 0.4,
    "leanRationale": "Discovered via dataset; lean assigned per item by analysis (not source-level).",
    "lang": "bn",
    "region": "BD-C",
    "regionLabel": "ঢাকা বিভাগ"
  },
  {
    "id": "bd-src-12",
    "title": "এসএ টিভি",
    "url": "https://www.satv.tv/feed/",
    "kind": "news",
    "topic": "world",
    "lean": null,
    "confidence": 0.4,
    "leanRationale": "Discovered via dataset; lean assigned per item by analysis (not source-level).",
    "lang": "bn",
    "region": "BD-C",
    "regionLabel": "ঢাকা বিভাগ"
  },
  {
    "id": "bd-src-13",
    "title": "মাছরাঙা টিভি",
    "url": "https://maasranga.tv/feed/",
    "kind": "news",
    "topic": "world",
    "lean": null,
    "confidence": 0.4,
    "leanRationale": "Discovered via dataset; lean assigned per item by analysis (not source-level).",
    "lang": "bn",
    "region": "BD-C",
    "regionLabel": "ঢাকা বিভাগ"
  },
  {
    "id": "bd-src-14",
    "title": "সাপ্তাহিক ব্লিটজ",
    "url": "http://www.weeklyblitz.net/feed",
    "kind": "news",
    "topic": "world",
    "lean": null,
    "confidence": 0.4,
    "leanRationale": "Discovered via dataset; lean assigned per item by analysis (not source-level).",
    "lang": "bn"
  },
  {
    "id": "bd-src-15",
    "title": "বাংলাদেশ প্রতিদিন",
    "url": "http://www.bd-pratidin.com/rss.xml",
    "kind": "news",
    "topic": "world",
    "lean": null,
    "confidence": 0.4,
    "leanRationale": "Discovered via dataset; lean assigned per item by analysis (not source-level).",
    "lang": "bn"
  },
  {
    "id": "bd-src-16",
    "title": "দৈনিক আজাদী",
    "url": "https://dainikazadi.net/feed/",
    "kind": "news",
    "topic": "world",
    "lean": null,
    "confidence": 0.4,
    "leanRationale": "Discovered via dataset; lean assigned per item by analysis (not source-level).",
    "lang": "bn"
  },
  {
    "id": "bd-src-17",
    "title": "নিউজ টুয়েন্টি ফোর",
    "url": "https://www.news24bd.tv/rss.xml",
    "kind": "news",
    "topic": "world",
    "lean": null,
    "confidence": 0.4,
    "leanRationale": "Discovered via dataset; lean assigned per item by analysis (not source-level).",
    "lang": "bn",
    "region": "BD-C",
    "regionLabel": "ঢাকা বিভাগ"
  },
  {
    "id": "bd-src-18",
    "title": "নাগরিক টিভি",
    "url": "https://nagorik.com/feed/",
    "kind": "news",
    "topic": "world",
    "lean": null,
    "confidence": 0.4,
    "leanRationale": "Discovered via dataset; lean assigned per item by analysis (not source-level).",
    "lang": "bn",
    "region": "BD-C",
    "regionLabel": "ঢাকা বিভাগ"
  },
  {
    "id": "bd-src-19",
    "title": "আনন্দ টিভি",
    "url": "https://anandatv.tv/feed/",
    "kind": "news",
    "topic": "world",
    "lean": null,
    "confidence": 0.4,
    "leanRationale": "Discovered via dataset; lean assigned per item by analysis (not source-level).",
    "lang": "bn",
    "region": "BD-C",
    "regionLabel": "ঢাকা বিভাগ"
  },
  {
    "id": "bd-src-20",
    "title": "দৈনিক টার্গেট",
    "url": "https://dainiktarget.com/feed/",
    "kind": "news",
    "topic": "world",
    "lean": null,
    "confidence": 0.4,
    "leanRationale": "Discovered via dataset; lean assigned per item by analysis (not source-level).",
    "lang": "bn",
    "region": "BD-C",
    "regionLabel": "ঢাকা বিভাগ"
  },
  {
    "id": "bd-src-21",
    "title": "আজকের পত্রিকা",
    "url": "http://ajkerpatrika.com/feed",
    "kind": "news",
    "topic": "world",
    "lean": null,
    "confidence": 0.4,
    "leanRationale": "Discovered via dataset; lean assigned per item by analysis (not source-level).",
    "lang": "bn",
    "region": "BD-C",
    "regionLabel": "ঢাকা বিভাগ"
  },
  {
    "id": "bd-src-22",
    "title": "দৈনিক আজকের দর্পণ",
    "url": "https://ajkerdarpon.com/feed",
    "kind": "news",
    "topic": "world",
    "lean": null,
    "confidence": 0.4,
    "leanRationale": "Discovered via dataset; lean assigned per item by analysis (not source-level).",
    "lang": "bn",
    "region": "BD-C",
    "regionLabel": "ঢাকা বিভাগ"
  },
  {
    "id": "bd-bangladesh-bulletin",
    "title": "Bangladesh Bulletin",
    "url": "https://www.bd-bulletin.com/rss",
    "kind": "news",
    "topic": "world",
    "lean": null,
    "confidence": 0.4,
    "leanRationale": "Discovered via dataset; lean assigned per item by analysis (not source-level).",
    "lang": "bn",
    "region": "BD-C",
    "regionLabel": "ঢাকা বিভাগ"
  },
  {
    "id": "bd-src-23",
    "title": "সে অলওয়েজ ট্রুথ",
    "url": "https://www.sayalwaystruth.com/feed",
    "kind": "news",
    "topic": "world",
    "lean": null,
    "confidence": 0.4,
    "leanRationale": "Discovered via dataset; lean assigned per item by analysis (not source-level).",
    "lang": "bn",
    "region": "BD-C",
    "regionLabel": "ঢাকা বিভাগ"
  },
  {
    "id": "bd-src-24",
    "title": "দৈনিক বজ্রশক্তি",
    "url": "https://bajroshakti.com/feed",
    "kind": "news",
    "topic": "world",
    "lean": null,
    "confidence": 0.4,
    "leanRationale": "Discovered via dataset; lean assigned per item by analysis (not source-level).",
    "lang": "bn"
  },
  {
    "id": "bd-app-com-pk",
    "title": "app.com.pk",
    "url": "http://app.com.pk/feed",
    "kind": "news",
    "topic": "world",
    "lean": null,
    "confidence": 0.4,
    "leanRationale": "Discovered via dataset; lean assigned per item by analysis (not source-level).",
    "lang": "bn"
  },
  {
    "id": "bd-fns24-com",
    "title": "fns24.com",
    "url": "http://www.fns24.com/rss",
    "kind": "news",
    "topic": "world",
    "lean": null,
    "confidence": 0.4,
    "leanRationale": "Discovered via dataset; lean assigned per item by analysis (not source-level).",
    "lang": "bn"
  },
  {
    "id": "bd-observerbd-com",
    "title": "observerbd.com",
    "url": "http://observerbd.com/rss",
    "kind": "news",
    "topic": "world",
    "lean": null,
    "confidence": 0.4,
    "leanRationale": "Discovered via dataset; lean assigned per item by analysis (not source-level).",
    "lang": "bn"
  },
  {
    "id": "bd-bartabazar-com",
    "title": "bartabazar.com",
    "url": "http://www.bartabazar.com/feed",
    "kind": "news",
    "topic": "world",
    "lean": null,
    "confidence": 0.4,
    "leanRationale": "Discovered via dataset; lean assigned per item by analysis (not source-level).",
    "lang": "bn"
  },
  {
    "id": "bd-deshebideshe-com",
    "title": "deshebideshe.com",
    "url": "http://deshebideshe.com/rss",
    "kind": "news",
    "topic": "world",
    "lean": null,
    "confidence": 0.4,
    "leanRationale": "Discovered via dataset; lean assigned per item by analysis (not source-level).",
    "lang": "bn"
  },
  {
    "id": "bd-patradoot-net",
    "title": "patradoot.net",
    "url": "https://patradoot.net/feed/",
    "kind": "news",
    "topic": "world",
    "lean": null,
    "confidence": 0.4,
    "leanRationale": "Discovered via dataset; lean assigned per item by analysis (not source-level).",
    "lang": "bn"
  },
  {
    "id": "bd-arthosuchak-com",
    "title": "arthosuchak.com",
    "url": "https://www.arthosuchak.com/feed/",
    "kind": "news",
    "topic": "world",
    "lean": null,
    "confidence": 0.4,
    "leanRationale": "Discovered via dataset; lean assigned per item by analysis (not source-level).",
    "lang": "bn"
  },
  {
    "id": "bd-mtnews24-com",
    "title": "mtnews24.com",
    "url": "http://mtnews24.com/feed",
    "kind": "news",
    "topic": "world",
    "lean": null,
    "confidence": 0.4,
    "leanRationale": "Discovered via dataset; lean assigned per item by analysis (not source-level).",
    "lang": "bn"
  },
  {
    "id": "bd-zoombangla-com",
    "title": "zoombangla.com",
    "url": "http://news.zoombangla.com/feed",
    "kind": "news",
    "topic": "world",
    "lean": null,
    "confidence": 0.4,
    "leanRationale": "Discovered via dataset; lean assigned per item by analysis (not source-level).",
    "lang": "bn"
  },
  {
    "id": "bd-dhakaprotidin-com",
    "title": "dhakaprotidin.com",
    "url": "https://www.dhakaprotidin.com/feed/",
    "kind": "news",
    "topic": "world",
    "lean": null,
    "confidence": 0.4,
    "leanRationale": "Discovered via dataset; lean assigned per item by analysis (not source-level).",
    "lang": "bn"
  },
  {
    "id": "bd-amaderbarisal-com",
    "title": "amaderbarisal.com",
    "url": "http://www.amaderbarisal.com/feed",
    "kind": "news",
    "topic": "world",
    "lean": null,
    "confidence": 0.4,
    "leanRationale": "Discovered via dataset; lean assigned per item by analysis (not source-level).",
    "lang": "bn"
  },
  {
    "id": "bd-dainiksylhet-com",
    "title": "dainiksylhet.com",
    "url": "http://dainiksylhet.com/feed",
    "kind": "news",
    "topic": "world",
    "lean": null,
    "confidence": 0.4,
    "leanRationale": "Discovered via dataset; lean assigned per item by analysis (not source-level).",
    "lang": "bn"
  },
  {
    "id": "bd-thepeoplesnews24-com",
    "title": "thepeoplesnews24.com",
    "url": "https://www.thepeoplesnews24.com/feed",
    "kind": "news",
    "topic": "world",
    "lean": null,
    "confidence": 0.4,
    "leanRationale": "Discovered via dataset; lean assigned per item by analysis (not source-level).",
    "lang": "bn"
  },
  {
    "id": "bd-shamolbangla24-com",
    "title": "shamolbangla24.com",
    "url": "http://shamolbangla24.com/feed",
    "kind": "news",
    "topic": "world",
    "lean": null,
    "confidence": 0.4,
    "leanRationale": "Discovered via dataset; lean assigned per item by analysis (not source-level).",
    "lang": "bn"
  },
  {
    "id": "bd-bangladeshchronicle-net",
    "title": "bangladeshchronicle.net",
    "url": "https://bangladeshchronicle.net/feed/",
    "kind": "news",
    "topic": "world",
    "lean": null,
    "confidence": 0.4,
    "leanRationale": "Discovered via dataset; lean assigned per item by analysis (not source-level).",
    "lang": "bn"
  },
  {
    "id": "bd-bdnewstimes-com",
    "title": "bdnewstimes.com",
    "url": "https://bdnewstimes.com/feed/",
    "kind": "news",
    "topic": "world",
    "lean": null,
    "confidence": 0.4,
    "leanRationale": "Discovered via dataset; lean assigned per item by analysis (not source-level).",
    "lang": "bn"
  },
  {
    "id": "bd-meherpurnews-com",
    "title": "meherpurnews.com",
    "url": "https://www.meherpurnews.com/feed/",
    "kind": "news",
    "topic": "world",
    "lean": null,
    "confidence": 0.4,
    "leanRationale": "Discovered via dataset; lean assigned per item by analysis (not source-level).",
    "lang": "bn"
  },
  {
    "id": "bd-alltimenews-com",
    "title": "alltimenews.com",
    "url": "http://www.alltimenews.com/feed",
    "kind": "news",
    "topic": "world",
    "lean": null,
    "confidence": 0.4,
    "leanRationale": "Discovered via dataset; lean assigned per item by analysis (not source-level).",
    "lang": "bn"
  },
  {
    "id": "bd-bd24live-com",
    "title": "bd24live.com",
    "url": "https://www.bd24live.com/feed/",
    "kind": "news",
    "topic": "world",
    "lean": null,
    "confidence": 0.4,
    "leanRationale": "Discovered via dataset; lean assigned per item by analysis (not source-level).",
    "lang": "bn"
  },
  {
    "id": "bd-vnewsbd-com",
    "title": "vnewsbd.com",
    "url": "https://vnewsbd.com/feed/",
    "kind": "news",
    "topic": "world",
    "lean": null,
    "confidence": 0.4,
    "leanRationale": "Discovered via dataset; lean assigned per item by analysis (not source-level).",
    "lang": "bn"
  },
  {
    "id": "bd-weeklysonarbangla-net",
    "title": "weeklysonarbangla.net",
    "url": "http://www.weeklysonarbangla.net/feed",
    "kind": "news",
    "topic": "world",
    "lean": null,
    "confidence": 0.4,
    "leanRationale": "Discovered via dataset; lean assigned per item by analysis (not source-level).",
    "lang": "bn"
  },
  {
    "id": "bd-newsgarden24-com",
    "title": "newsgarden24.com",
    "url": "https://newsgarden24.com/feed",
    "kind": "news",
    "topic": "world",
    "lean": null,
    "confidence": 0.4,
    "leanRationale": "Discovered via dataset; lean assigned per item by analysis (not source-level).",
    "lang": "bn"
  },
  {
    "id": "bd-purbanchal-com",
    "title": "purbanchal.com",
    "url": "https://purbanchal.com/feed/",
    "kind": "news",
    "topic": "world",
    "lean": null,
    "confidence": 0.4,
    "leanRationale": "Discovered via dataset; lean assigned per item by analysis (not source-level).",
    "lang": "bn"
  },
  {
    "id": "bd-thegoodmorning-net",
    "title": "thegoodmorning.net",
    "url": "https://thegoodmorning.net/feed",
    "kind": "news",
    "topic": "world",
    "lean": null,
    "confidence": 0.4,
    "leanRationale": "Discovered via dataset; lean assigned per item by analysis (not source-level).",
    "lang": "bn"
  },
  {
    "id": "bd-natunsomoy-net",
    "title": "natunsomoy.net",
    "url": "https://www.natunsomoy.net/rss.xml",
    "kind": "news",
    "topic": "world",
    "lean": null,
    "confidence": 0.4,
    "leanRationale": "Discovered via dataset; lean assigned per item by analysis (not source-level).",
    "lang": "bn"
  },
  {
    "id": "bd-sharebarta24-com",
    "title": "sharebarta24.com",
    "url": "http://www.sharebarta24.com/feed",
    "kind": "news",
    "topic": "world",
    "lean": null,
    "confidence": 0.4,
    "leanRationale": "Discovered via dataset; lean assigned per item by analysis (not source-level).",
    "lang": "bn"
  },
  {
    "id": "bd-latestbdnews-com",
    "title": "latestbdnews.com",
    "url": "https://www.latestbdnews.com/feed/",
    "kind": "news",
    "topic": "world",
    "lean": null,
    "confidence": 0.4,
    "leanRationale": "Discovered via dataset; lean assigned per item by analysis (not source-level).",
    "lang": "bn"
  },
  {
    "id": "bd-news71online-com",
    "title": "news71online.com",
    "url": "http://www.news71online.com/feed",
    "kind": "news",
    "topic": "world",
    "lean": null,
    "confidence": 0.4,
    "leanRationale": "Discovered via dataset; lean assigned per item by analysis (not source-level).",
    "lang": "bn"
  },
  {
    "id": "bd-amar-sangbad-com",
    "title": "amar-sangbad.com",
    "url": "https://www.amar-sangbad.com/feed/",
    "kind": "news",
    "topic": "world",
    "lean": null,
    "confidence": 0.4,
    "leanRationale": "Discovered via dataset; lean assigned per item by analysis (not source-level).",
    "lang": "bn"
  },
  {
    "id": "bd-sheershasangbad-com",
    "title": "sheershasangbad.com",
    "url": "http://www.sheershasangbad.com/feed",
    "kind": "news",
    "topic": "world",
    "lean": null,
    "confidence": 0.4,
    "leanRationale": "Discovered via dataset; lean assigned per item by analysis (not source-level).",
    "lang": "bn"
  },
  {
    "id": "bd-thekushtiatimes-com",
    "title": "thekushtiatimes.com",
    "url": "https://thekushtiatimes.com/feed/",
    "kind": "news",
    "topic": "world",
    "lean": null,
    "confidence": 0.4,
    "leanRationale": "Discovered via dataset; lean assigned per item by analysis (not source-level).",
    "lang": "bn"
  },
  {
    "id": "bd-bdtype-com",
    "title": "bdtype.com",
    "url": "https://bdtype.com/feed",
    "kind": "news",
    "topic": "world",
    "lean": null,
    "confidence": 0.4,
    "leanRationale": "Discovered via dataset; lean assigned per item by analysis (not source-level).",
    "lang": "bn"
  },
  {
    "id": "bd-anb24-net",
    "title": "anb24.net",
    "url": "https://anb24.net/feed/",
    "kind": "news",
    "topic": "world",
    "lean": null,
    "confidence": 0.4,
    "leanRationale": "Discovered via dataset; lean assigned per item by analysis (not source-level).",
    "lang": "bn"
  },
  {
    "id": "bd-bartabangla-com",
    "title": "bartabangla.com",
    "url": "https://bartabangla.com/feed/",
    "kind": "news",
    "topic": "world",
    "lean": null,
    "confidence": 0.4,
    "leanRationale": "Discovered via dataset; lean assigned per item by analysis (not source-level).",
    "lang": "bn"
  },
  {
    "id": "bd-crimebarta-com",
    "title": "crimebarta.com",
    "url": "https://crimebarta.com/feed/",
    "kind": "news",
    "topic": "world",
    "lean": null,
    "confidence": 0.4,
    "leanRationale": "Discovered via dataset; lean assigned per item by analysis (not source-level).",
    "lang": "bn"
  },
  {
    "id": "bd-agrodristi-com",
    "title": "agrodristi.com",
    "url": "http://agrodristi.com/feed",
    "kind": "news",
    "topic": "world",
    "lean": null,
    "confidence": 0.4,
    "leanRationale": "Discovered via dataset; lean assigned per item by analysis (not source-level).",
    "lang": "bn"
  },
  {
    "id": "bd-maguranews-com",
    "title": "maguranews.com",
    "url": "https://www.maguranews.com/feed/",
    "kind": "news",
    "topic": "world",
    "lean": null,
    "confidence": 0.4,
    "leanRationale": "Discovered via dataset; lean assigned per item by analysis (not source-level).",
    "lang": "bn"
  },
  {
    "id": "bd-tulpar24-com",
    "title": "tulpar24.com",
    "url": "http://tulpar24.com/feed",
    "kind": "news",
    "topic": "world",
    "lean": null,
    "confidence": 0.4,
    "leanRationale": "Discovered via dataset; lean assigned per item by analysis (not source-level).",
    "lang": "bn"
  },
  {
    "id": "bd-ctgtimes-com",
    "title": "ctgtimes.com",
    "url": "https://ctgtimes.com/feed",
    "kind": "news",
    "topic": "world",
    "lean": null,
    "confidence": 0.4,
    "leanRationale": "Discovered via dataset; lean assigned per item by analysis (not source-level).",
    "lang": "bn"
  },
  {
    "id": "bd-thebangladeshtoday-com",
    "title": "thebangladeshtoday.com",
    "url": "https://thebangladeshtoday.com/?feed=rss2",
    "kind": "news",
    "topic": "world",
    "lean": null,
    "confidence": 0.4,
    "leanRationale": "Discovered via dataset; lean assigned per item by analysis (not source-level).",
    "lang": "bn"
  },
  {
    "id": "bd-timewatch-com-bd",
    "title": "timewatch.com.bd",
    "url": "http://www.timewatch.com.bd/?feed=rss2",
    "kind": "news",
    "topic": "world",
    "lean": null,
    "confidence": 0.4,
    "leanRationale": "Discovered via dataset; lean assigned per item by analysis (not source-level).",
    "lang": "bn"
  },
  {
    "id": "bd-ourtimebd-com",
    "title": "ourtimebd.com",
    "url": "https://ourtimebd.com/feed/",
    "kind": "news",
    "topic": "world",
    "lean": null,
    "confidence": 0.4,
    "leanRationale": "Discovered via dataset; lean assigned per item by analysis (not source-level).",
    "lang": "bn"
  },
  {
    "id": "bd-khulnanews-com",
    "title": "khulnanews.com",
    "url": "https://khulnanews.com/feed/",
    "kind": "news",
    "topic": "world",
    "lean": null,
    "confidence": 0.4,
    "leanRationale": "Discovered via dataset; lean assigned per item by analysis (not source-level).",
    "lang": "bn"
  },
  {
    "id": "bd-bdview24-com",
    "title": "bdview24.com",
    "url": "https://www.bdview24.com/feed/",
    "kind": "news",
    "topic": "world",
    "lean": null,
    "confidence": 0.4,
    "leanRationale": "Discovered via dataset; lean assigned per item by analysis (not source-level).",
    "lang": "bn"
  },
  {
    "id": "bd-dhakatribune-com",
    "title": "dhakatribune.com",
    "url": "http://dhakatribune.com/feed/",
    "kind": "news",
    "topic": "world",
    "lean": null,
    "confidence": 0.4,
    "leanRationale": "Discovered via dataset; lean assigned per item by analysis (not source-level).",
    "lang": "bn"
  },
  {
    "id": "bd-bangladeshtimes24-com",
    "title": "bangladeshtimes24.com",
    "url": "https://bangladeshtimes24.com/feed/",
    "kind": "news",
    "topic": "world",
    "lean": null,
    "confidence": 0.4,
    "leanRationale": "Discovered via dataset; lean assigned per item by analysis (not source-level).",
    "lang": "bn"
  },
  {
    "id": "bd-banglanews24-com",
    "title": "banglanews24.com",
    "url": "http://www.banglanews24.com/rss.xml",
    "kind": "news",
    "topic": "world",
    "lean": null,
    "confidence": 0.4,
    "leanRationale": "Discovered via dataset; lean assigned per item by analysis (not source-level).",
    "lang": "bn"
  },
  {
    "id": "bd-ittefaq-com-bd",
    "title": "ittefaq.com.bd",
    "url": "http://ittefaq.com.bd/feed/",
    "kind": "news",
    "topic": "world",
    "lean": null,
    "confidence": 0.4,
    "leanRationale": "Discovered via dataset; lean assigned per item by analysis (not source-level).",
    "lang": "bn"
  },
  {
    "id": "bd-1newsbd-com",
    "title": "1newsbd.com",
    "url": "https://www.onenewsbd.com/feed",
    "kind": "news",
    "topic": "world",
    "lean": null,
    "confidence": 0.4,
    "leanRationale": "Discovered via dataset; lean assigned per item by analysis (not source-level).",
    "lang": "bn"
  },
  {
    "id": "bd-amaderorthoneeti-com",
    "title": "amaderorthoneeti.com",
    "url": "https://amaderorthoneeti.com/feed/",
    "kind": "news",
    "topic": "world",
    "lean": null,
    "confidence": 0.4,
    "leanRationale": "Discovered via dataset; lean assigned per item by analysis (not source-level).",
    "lang": "bn"
  },
  {
    "id": "bd-thedailysangbad-com",
    "title": "thedailysangbad.com",
    "url": "https://www.thedailysangbad.com/feed/",
    "kind": "news",
    "topic": "world",
    "lean": null,
    "confidence": 0.4,
    "leanRationale": "Discovered via dataset; lean assigned per item by analysis (not source-level).",
    "lang": "bn"
  },
  {
    "id": "bd-businessleader-club",
    "title": "businessleader.club",
    "url": "http://www.businessleader.club/?feed=rss2",
    "kind": "news",
    "topic": "world",
    "lean": null,
    "confidence": 0.4,
    "leanRationale": "Discovered via dataset; lean assigned per item by analysis (not source-level).",
    "lang": "bn"
  },
  {
    "id": "bd-crimeexpress24-com",
    "title": "crimeexpress24.com",
    "url": "https://crimeexpress24.com/feed/",
    "kind": "news",
    "topic": "world",
    "lean": null,
    "confidence": 0.4,
    "leanRationale": "Discovered via dataset; lean assigned per item by analysis (not source-level).",
    "lang": "bn"
  },
  {
    "id": "bd-gnewsbd24-com",
    "title": "gnewsbd24.com",
    "url": "https://gnewsbd24.com/feed/",
    "kind": "news",
    "topic": "world",
    "lean": null,
    "confidence": 0.4,
    "leanRationale": "Discovered via dataset; lean assigned per item by analysis (not source-level).",
    "lang": "bn"
  },
  {
    "id": "bd-dailybangladeshbani-com",
    "title": "dailybangladeshbani.com",
    "url": "https://dailybangladeshbani.com/?feed=rss2",
    "kind": "news",
    "topic": "world",
    "lean": null,
    "confidence": 0.4,
    "leanRationale": "Discovered via dataset; lean assigned per item by analysis (not source-level).",
    "lang": "bn"
  },
  {
    "id": "bd-barisaltoday-com",
    "title": "barisaltoday.com",
    "url": "https://barisaltoday.com/feed/",
    "kind": "news",
    "topic": "world",
    "lean": null,
    "confidence": 0.4,
    "leanRationale": "Discovered via dataset; lean assigned per item by analysis (not source-level).",
    "lang": "bn"
  },
  {
    "id": "bd-ennayadiganta-com",
    "title": "ennayadiganta.com",
    "url": "http://www.ennayadiganta.com/rss",
    "kind": "news",
    "topic": "world",
    "lean": null,
    "confidence": 0.4,
    "leanRationale": "Discovered via dataset; lean assigned per item by analysis (not source-level).",
    "lang": "bn"
  },
  {
    "id": "bd-onabil-net",
    "title": "onabil.net",
    "url": "https://onabil.net/?feed=rss2",
    "kind": "news",
    "topic": "world",
    "lean": null,
    "confidence": 0.4,
    "leanRationale": "Discovered via dataset; lean assigned per item by analysis (not source-level).",
    "lang": "bn"
  },
  {
    "id": "bd-ajkerkhobor-net",
    "title": "ajkerkhobor.net",
    "url": "https://ajkerkhobor.net/feed",
    "kind": "news",
    "topic": "world",
    "lean": null,
    "confidence": 0.4,
    "leanRationale": "Discovered via dataset; lean assigned per item by analysis (not source-level).",
    "lang": "bn"
  },
  {
    "id": "bd-newsworldbd-com",
    "title": "newsworldbd.com",
    "url": "http://www.newsworldbd.com/?feed=rss2",
    "kind": "news",
    "topic": "world",
    "lean": null,
    "confidence": 0.4,
    "leanRationale": "Discovered via dataset; lean assigned per item by analysis (not source-level).",
    "lang": "bn"
  },
  {
    "id": "bd-ournewsbd-com",
    "title": "ournewsbd.com",
    "url": "http://ournewsbd.com/feed",
    "kind": "news",
    "topic": "world",
    "lean": null,
    "confidence": 0.4,
    "leanRationale": "Discovered via dataset; lean assigned per item by analysis (not source-level).",
    "lang": "bn"
  },
  {
    "id": "bd-sylhetnewsonline-com",
    "title": "sylhetnewsonline.com",
    "url": "http://www.sylhetnewsonline.com/rss.xml",
    "kind": "news",
    "topic": "world",
    "lean": null,
    "confidence": 0.4,
    "leanRationale": "Discovered via dataset; lean assigned per item by analysis (not source-level).",
    "lang": "bn"
  },
  {
    "id": "bd-dailysharebiz-net",
    "title": "dailysharebiz.net",
    "url": "https://www.dailysharebiz.net/feed/",
    "kind": "news",
    "topic": "world",
    "lean": null,
    "confidence": 0.4,
    "leanRationale": "Discovered via dataset; lean assigned per item by analysis (not source-level).",
    "lang": "bn"
  },
  {
    "id": "bd-bangladeshshomoy-com",
    "title": "bangladeshshomoy.com",
    "url": "https://bangladeshshomoy.com/feed/",
    "kind": "news",
    "topic": "world",
    "lean": null,
    "confidence": 0.4,
    "leanRationale": "Discovered via dataset; lean assigned per item by analysis (not source-level).",
    "lang": "bn"
  },
  {
    "id": "bd-blacknews-com",
    "title": "blacknews.com",
    "url": "https://blacknews.com/feed/",
    "kind": "news",
    "topic": "world",
    "lean": null,
    "confidence": 0.4,
    "leanRationale": "Discovered via dataset; lean assigned per item by analysis (not source-level).",
    "lang": "bn"
  },
  {
    "id": "bd-bangladesh-web-com",
    "title": "bangladesh-web.com",
    "url": "https://bangladesh-web.com/feed/",
    "kind": "news",
    "topic": "world",
    "lean": null,
    "confidence": 0.4,
    "leanRationale": "Discovered via dataset; lean assigned per item by analysis (not source-level).",
    "lang": "bn"
  },
  {
    "id": "bd-mayerdak-com",
    "title": "mayerdak.com",
    "url": "http://mayerdak.com/feed",
    "kind": "news",
    "topic": "world",
    "lean": null,
    "confidence": 0.4,
    "leanRationale": "Discovered via dataset; lean assigned per item by analysis (not source-level).",
    "lang": "bn"
  }
]
