[
  {
    "id": "ge-src",
    "title": "მზე",
    "url": "https://tvmze.ge/index.php?mod=rss",
    "kind": "news",
    "topic": "world",
    "lean": null,
    "confidence": 0.4,
    "leanRationale": "Discovered via dataset; lean assigned per item by analysis (not source-level).",
    "lang": "ka",
    "region": "GE-TB",
    "regionLabel": "თბილისი"
  },
  {
    "id": "ge-vrastan",
    "title": "Vrastan",
    "url": "http://www.vrastan.ge/index.php?format=feed&amp;type=rss",
    "kind": "news",
    "topic": "world",
    "lean": null,
    "confidence": 0.4,
    "leanRationale": "Discovered via dataset; lean assigned per item by analysis (not source-level).",
    "lang": "ka",
    "region": "GE-TB",
    "regionLabel": "თბილისი"
  },
  {
    "id": "ge-src-2",
    "title": "კაუკაზიშე პოსტი",
    "url": "http://www.kaukasische-post.com/?feed=rss2",
    "kind": "news",
    "topic": "world",
    "lean": null,
    "confidence": 0.4,
    "leanRationale": "Discovered via dataset; lean assigned per item by analysis (not source-level).",
    "lang": "ka"
  },
  {
    "id": "ge-anna",
    "title": "ANNA",
    "url": "https://anna-news.info/feed/",
    "kind": "news",
    "topic": "world",
    "lean": null,
    "confidence": 0.4,
    "leanRationale": "Discovered via dataset; lean assigned per item by analysis (not source-level).",
    "lang": "ka"
  },
  {
    "id": "ge-src-3",
    "title": "სივილ ჯორჯია",
    "url": "https://civil.ge/feed",
    "kind": "news",
    "topic": "world",
    "lean": null,
    "confidence": 0.4,
    "leanRationale": "Discovered via dataset; lean assigned per item by analysis (not source-level).",
    "lang": "ka",
    "region": "GE-TB",
    "regionLabel": "თბილისი"
  },
  {
    "id": "ge-ghn",
    "title": "GHN",
    "url": "http://www.ghn.ge/rss",
    "kind": "news",
    "topic": "world",
    "lean": null,
    "confidence": 0.4,
    "leanRationale": "Discovered via dataset; lean assigned per item by analysis (not source-level).",
    "lang": "ka",
    "region": "GE-TB",
    "regionLabel": "თბილისი"
  },
  {
    "id": "ge-marketbeat-com",
    "title": "marketbeat.com",
    "url": "https://www.marketbeat.com/rss.ashx?type=headlines",
    "kind": "news",
    "topic": "world",
    "lean": null,
    "confidence": 0.4,
    "leanRationale": "Discovered via dataset; lean assigned per item by analysis (not source-level).",
    "lang": "ka"
  },
  {
    "id": "ge-gpb-org",
    "title": "gpb.org",
    "url": "http://www.gpb.org/rss",
    "kind": "news",
    "topic": "world",
    "lean": null,
    "confidence": 0.4,
    "leanRationale": "Discovered via dataset; lean assigned per item by analysis (not source-level).",
    "lang": "ka"
  },
  {
    "id": "ge-41nbc-com",
    "title": "41nbc.com",
    "url": "https://www.41nbc.com/feed/",
    "kind": "news",
    "topic": "world",
    "lean": null,
    "confidence": 0.4,
    "leanRationale": "Discovered via dataset; lean assigned per item by analysis (not source-level).",
    "lang": "ka"
  },
  {
    "id": "ge-coosavalleynews-com",
    "title": "coosavalleynews.com",
    "url": "https://coosavalleynews.com/feed/",
    "kind": "news",
    "topic": "world",
    "lean": null,
    "confidence": 0.4,
    "leanRationale": "Discovered via dataset; lean assigned per item by analysis (not source-level).",
    "lang": "ka"
  },
  {
    "id": "ge-albanyherald-com",
    "title": "albanyherald.com",
    "url": "http://albanyherald.com/feed",
    "kind": "news",
    "topic": "world",
    "lean": null,
    "confidence": 0.4,
    "leanRationale": "Discovered via dataset; lean assigned per item by analysis (not source-level).",
    "lang": "ka"
  },
  {
    "id": "ge-valdostadailytimes-com",
    "title": "valdostadailytimes.com",
    "url": "http://valdostadailytimes.com/feed",
    "kind": "news",
    "topic": "world",
    "lean": null,
    "confidence": 0.4,
    "leanRationale": "Discovered via dataset; lean assigned per item by analysis (not source-level).",
    "lang": "ka"
  },
  {
    "id": "ge-thegeorgiasun-com",
    "title": "thegeorgiasun.com",
    "url": "http://thegeorgiasun.com/feed",
    "kind": "news",
    "topic": "world",
    "lean": null,
    "confidence": 0.4,
    "leanRationale": "Discovered via dataset; lean assigned per item by analysis (not source-level).",
    "lang": "ka"
  },
  {
    "id": "ge-lagrangenews-com",
    "title": "lagrangenews.com",
    "url": "http://lagrangenews.com/rss.xml",
    "kind": "news",
    "topic": "world",
    "lean": null,
    "confidence": 0.4,
    "leanRationale": "Discovered via dataset; lean assigned per item by analysis (not source-level).",
    "lang": "ka"
  },
  {
    "id": "ge-gainesvilletimes-com",
    "title": "gainesvilletimes.com",
    "url": "http://www.gainesvilletimes.com/rss/",
    "kind": "news",
    "topic": "world",
    "lean": null,
    "confidence": 0.4,
    "leanRationale": "Discovered via dataset; lean assigned per item by analysis (not source-level).",
    "lang": "ka"
  },
  {
    "id": "ge-statesboroherald-com",
    "title": "statesboroherald.com",
    "url": "http://www.statesboroherald.com/rss/",
    "kind": "news",
    "topic": "world",
    "lean": null,
    "confidence": 0.4,
    "leanRationale": "Discovered via dataset; lean assigned per item by analysis (not source-level).",
    "lang": "ka"
  },
  {
    "id": "ge-moultrieobserver-com",
    "title": "moultrieobserver.com",
    "url": "http://moultrieobserver.com/feed",
    "kind": "news",
    "topic": "world",
    "lean": null,
    "confidence": 0.4,
    "leanRationale": "Discovered via dataset; lean assigned per item by analysis (not source-level).",
    "lang": "ka"
  },
  {
    "id": "ge-thecitizen-com",
    "title": "thecitizen.com",
    "url": "https://thecitizen.com/feed/",
    "kind": "news",
    "topic": "world",
    "lean": null,
    "confidence": 0.4,
    "leanRationale": "Discovered via dataset; lean assigned per item by analysis (not source-level).",
    "lang": "ka"
  },
  {
    "id": "ge-tiftongazette-com",
    "title": "tiftongazette.com",
    "url": "http://tiftongazette.com/feed",
    "kind": "news",
    "topic": "world",
    "lean": null,
    "confidence": 0.4,
    "leanRationale": "Discovered via dataset; lean assigned per item by analysis (not source-level).",
    "lang": "ka"
  },
  {
    "id": "ge-unionrecorder-com",
    "title": "unionrecorder.com",
    "url": "http://unionrecorder.com/feed",
    "kind": "news",
    "topic": "world",
    "lean": null,
    "confidence": 0.4,
    "leanRationale": "Discovered via dataset; lean assigned per item by analysis (not source-level).",
    "lang": "ka"
  },
  {
    "id": "ge-valdostatoday-com",
    "title": "valdostatoday.com",
    "url": "https://valdostatoday.com/feed/",
    "kind": "news",
    "topic": "world",
    "lean": null,
    "confidence": 0.4,
    "leanRationale": "Discovered via dataset; lean assigned per item by analysis (not source-level).",
    "lang": "ka"
  },
  {
    "id": "ge-theatlantavoice-com",
    "title": "theatlantavoice.com",
    "url": "https://theatlantavoice.com/feed/",
    "kind": "news",
    "topic": "world",
    "lean": null,
    "confidence": 0.4,
    "leanRationale": "Discovered via dataset; lean assigned per item by analysis (not source-level).",
    "lang": "ka"
  },
  {
    "id": "ge-atlantamagazine-com",
    "title": "atlantamagazine.com",
    "url": "https://www.atlantamagazine.com/feed/",
    "kind": "news",
    "topic": "world",
    "lean": null,
    "confidence": 0.4,
    "leanRationale": "Discovered via dataset; lean assigned per item by analysis (not source-level).",
    "lang": "ka"
  },
  {
    "id": "ge-covnews-com",
    "title": "covnews.com",
    "url": "http://covnews.com/rss/",
    "kind": "news",
    "topic": "world",
    "lean": null,
    "confidence": 0.4,
    "leanRationale": "Discovered via dataset; lean assigned per item by analysis (not source-level).",
    "lang": "ka"
  },
  {
    "id": "ge-thewiregrassfarmer-com",
    "title": "thewiregrassfarmer.com",
    "url": "https://www.thewiregrassfarmer.com/feed/",
    "kind": "news",
    "topic": "world",
    "lean": null,
    "confidence": 0.4,
    "leanRationale": "Discovered via dataset; lean assigned per item by analysis (not source-level).",
    "lang": "ka"
  },
  {
    "id": "ge-coastalcourier-com",
    "title": "coastalcourier.com",
    "url": "http://coastalcourier.com/rss/",
    "kind": "news",
    "topic": "world",
    "lean": null,
    "confidence": 0.4,
    "leanRationale": "Discovered via dataset; lean assigned per item by analysis (not source-level).",
    "lang": "ka"
  },
  {
    "id": "ge-oconeeenterprise-com",
    "title": "oconeeenterprise.com",
    "url": "https://www.oconeeenterprise.com/feed/",
    "kind": "news",
    "topic": "world",
    "lean": null,
    "confidence": 0.4,
    "leanRationale": "Discovered via dataset; lean assigned per item by analysis (not source-level).",
    "lang": "ka"
  },
  {
    "id": "ge-bryancountynews-com",
    "title": "bryancountynews.com",
    "url": "http://bryancountynews.com/rss/",
    "kind": "news",
    "topic": "world",
    "lean": null,
    "confidence": 0.4,
    "leanRationale": "Discovered via dataset; lean assigned per item by analysis (not source-level).",
    "lang": "ka"
  },
  {
    "id": "ge-timesenterprise-com",
    "title": "timesenterprise.com",
    "url": "http://timesenterprise.com/feed",
    "kind": "news",
    "topic": "world",
    "lean": null,
    "confidence": 0.4,
    "leanRationale": "Discovered via dataset; lean assigned per item by analysis (not source-level).",
    "lang": "ka"
  },
  {
    "id": "ge-thepostsearchlight-com",
    "title": "thepostsearchlight.com",
    "url": "http://thepostsearchlight.com/feed",
    "kind": "news",
    "topic": "world",
    "lean": null,
    "confidence": 0.4,
    "leanRationale": "Discovered via dataset; lean assigned per item by analysis (not source-level).",
    "lang": "ka"
  },
  {
    "id": "ge-theadvancenews-com",
    "title": "theadvancenews.com",
    "url": "http://www.theadvancenews.com/feed",
    "kind": "news",
    "topic": "world",
    "lean": null,
    "confidence": 0.4,
    "leanRationale": "Discovered via dataset; lean assigned per item by analysis (not source-level).",
    "lang": "ka"
  },
  {
    "id": "ge-13wmaz-com",
    "title": "13wmaz.com",
    "url": "https://www.youtube.com/feeds/videos.xml?channel_id=UCRNf0_t4Qo5eojj8sSvd_8A",
    "kind": "news",
    "topic": "world",
    "lean": null,
    "confidence": 0.4,
    "leanRationale": "Discovered via dataset; lean assigned per item by analysis (not source-level).",
    "lang": "ka"
  },
  {
    "id": "ge-theislanderonline-com",
    "title": "theislanderonline.com",
    "url": "https://www.theislanderonline.com/feed/",
    "kind": "news",
    "topic": "world",
    "lean": null,
    "confidence": 0.4,
    "leanRationale": "Discovered via dataset; lean assigned per item by analysis (not source-level).",
    "lang": "ka"
  },
  {
    "id": "ge-davidatlanta-com",
    "title": "davidatlanta.com",
    "url": "https://www.davidatlanta.com/feed/",
    "kind": "news",
    "topic": "world",
    "lean": null,
    "confidence": 0.4,
    "leanRationale": "Discovered via dataset; lean assigned per item by analysis (not source-level).",
    "lang": "ka"
  },
  {
    "id": "ge-forsythnews-com",
    "title": "forsythnews.com",
    "url": "http://forsythnews.com/rss/",
    "kind": "news",
    "topic": "world",
    "lean": null,
    "confidence": 0.4,
    "leanRationale": "Discovered via dataset; lean assigned per item by analysis (not source-level).",
    "lang": "ka"
  },
  {
    "id": "ge-georgiatrend-com",
    "title": "georgiatrend.com",
    "url": "https://www.georgiatrend.com/feed/",
    "kind": "news",
    "topic": "world",
    "lean": null,
    "confidence": 0.4,
    "leanRationale": "Discovered via dataset; lean assigned per item by analysis (not source-level).",
    "lang": "ka"
  },
  {
    "id": "ge-sowegalive-com",
    "title": "sowegalive.com",
    "url": "https://sowegalive.com/feed/",
    "kind": "news",
    "topic": "world",
    "lean": null,
    "confidence": 0.4,
    "leanRationale": "Discovered via dataset; lean assigned per item by analysis (not source-level).",
    "lang": "ka"
  },
  {
    "id": "ge-georgiabulletin-org",
    "title": "georgiabulletin.org",
    "url": "https://georgiabulletin.org/feed/",
    "kind": "news",
    "topic": "world",
    "lean": null,
    "confidence": 0.4,
    "leanRationale": "Discovered via dataset; lean assigned per item by analysis (not source-level).",
    "lang": "ka"
  },
  {
    "id": "ge-themonticellonews-com",
    "title": "themonticellonews.com",
    "url": "https://www.themonticellonews.com/feed/",
    "kind": "news",
    "topic": "world",
    "lean": null,
    "confidence": 0.4,
    "leanRationale": "Discovered via dataset; lean assigned per item by analysis (not source-level).",
    "lang": "ka"
  },
  {
    "id": "ge-dawsonnews-com",
    "title": "dawsonnews.com",
    "url": "http://dawsonnews.com/rss/",
    "kind": "news",
    "topic": "world",
    "lean": null,
    "confidence": 0.4,
    "leanRationale": "Discovered via dataset; lean assigned per item by analysis (not source-level).",
    "lang": "ka"
  },
  {
    "id": "ge-thedariennews-net",
    "title": "thedariennews.net",
    "url": "https://www.thedariennews.net/feed/",
    "kind": "news",
    "topic": "world",
    "lean": null,
    "confidence": 0.4,
    "leanRationale": "Discovered via dataset; lean assigned per item by analysis (not source-level).",
    "lang": "ka"
  },
  {
    "id": "ge-effinghamherald-net",
    "title": "effinghamherald.net",
    "url": "http://effinghamherald.net/rss/",
    "kind": "news",
    "topic": "world",
    "lean": null,
    "confidence": 0.4,
    "leanRationale": "Discovered via dataset; lean assigned per item by analysis (not source-level).",
    "lang": "ka"
  },
  {
    "id": "ge-atlantatribune-com",
    "title": "atlantatribune.com",
    "url": "https://atlantatribune.com/feed/",
    "kind": "news",
    "topic": "world",
    "lean": null,
    "confidence": 0.4,
    "leanRationale": "Discovered via dataset; lean assigned per item by analysis (not source-level).",
    "lang": "ka"
  },
  {
    "id": "ge-connectsavannah-com",
    "title": "connectsavannah.com",
    "url": "https://www.connectsavannah.com/feed/",
    "kind": "news",
    "topic": "world",
    "lean": null,
    "confidence": 0.4,
    "leanRationale": "Discovered via dataset; lean assigned per item by analysis (not source-level).",
    "lang": "ka"
  },
  {
    "id": "ge-adelnewstribune-com",
    "title": "adelnewstribune.com",
    "url": "https://www.adelnewstribune.com/feed/",
    "kind": "news",
    "topic": "world",
    "lean": null,
    "confidence": 0.4,
    "leanRationale": "Discovered via dataset; lean assigned per item by analysis (not source-level).",
    "lang": "ka"
  },
  {
    "id": "ge-11alive-com",
    "title": "11alive.com",
    "url": "https://www.youtube.com/feeds/videos.xml?channel_id=UCzF4Ryn8TKn64md77gS5Q5Q",
    "kind": "news",
    "topic": "world",
    "lean": null,
    "confidence": 0.4,
    "leanRationale": "Discovered via dataset; lean assigned per item by analysis (not source-level).",
    "lang": "ka"
  },
  {
    "id": "ge-theclinchcountynews-com",
    "title": "theclinchcountynews.com",
    "url": "https://www.theclinchcountynews.com/feed/",
    "kind": "news",
    "topic": "world",
    "lean": null,
    "confidence": 0.4,
    "leanRationale": "Discovered via dataset; lean assigned per item by analysis (not source-level).",
    "lang": "ka"
  },
  {
    "id": "ge-savannahmagazine-com",
    "title": "savannahmagazine.com",
    "url": "https://savannahmagazine.com/feed/",
    "kind": "news",
    "topic": "world",
    "lean": null,
    "confidence": 0.4,
    "leanRationale": "Discovered via dataset; lean assigned per item by analysis (not source-level).",
    "lang": "ka"
  },
  {
    "id": "ge-theocillastar-com",
    "title": "theocillastar.com",
    "url": "https://www.theocillastar.com/feed/",
    "kind": "news",
    "topic": "world",
    "lean": null,
    "confidence": 0.4,
    "leanRationale": "Discovered via dataset; lean assigned per item by analysis (not source-level).",
    "lang": "ka"
  },
  {
    "id": "ge-tallapoosa-journal-com",
    "title": "tallapoosa-journal.com",
    "url": "http://www.tallapoosa-journal.com/feed/",
    "kind": "news",
    "topic": "world",
    "lean": null,
    "confidence": 0.4,
    "leanRationale": "Discovered via dataset; lean assigned per item by analysis (not source-level).",
    "lang": "ka"
  },
  {
    "id": "ge-showcasepublicationsga-com",
    "title": "showcasepublicationsga.com",
    "url": "https://showcasepublicationsga.com/feed",
    "kind": "news",
    "topic": "world",
    "lean": null,
    "confidence": 0.4,
    "leanRationale": "Discovered via dataset; lean assigned per item by analysis (not source-level).",
    "lang": "ka"
  },
  {
    "id": "ge-thegavoice-com",
    "title": "thegavoice.com",
    "url": "https://roughdraftatlanta.com/feed/",
    "kind": "news",
    "topic": "world",
    "lean": null,
    "confidence": 0.4,
    "leanRationale": "Discovered via dataset; lean assigned per item by analysis (not source-level).",
    "lang": "ka"
  },
  {
    "id": "ge-jdledger-com",
    "title": "jdledger.com",
    "url": "https://www.jdledger.com/feed/",
    "kind": "news",
    "topic": "world",
    "lean": null,
    "confidence": 0.4,
    "leanRationale": "Discovered via dataset; lean assigned per item by analysis (not source-level).",
    "lang": "ka"
  },
  {
    "id": "ge-myfoxatlanta-com",
    "title": "myfoxatlanta.com",
    "url": "https://www.fox5atlanta.com/rss/category/news",
    "kind": "news",
    "topic": "world",
    "lean": null,
    "confidence": 0.4,
    "leanRationale": "Discovered via dataset; lean assigned per item by analysis (not source-level).",
    "lang": "ka"
  },
  {
    "id": "ge-dbiradio-com",
    "title": "dbiradio.com",
    "url": "https://www.dbiradio.com/feed/",
    "kind": "news",
    "topic": "world",
    "lean": null,
    "confidence": 0.4,
    "leanRationale": "Discovered via dataset; lean assigned per item by analysis (not source-level).",
    "lang": "ka"
  },
  {
    "id": "ge-atlinq-com",
    "title": "atlinq.com",
    "url": "https://atlinq.com/feed/",
    "kind": "news",
    "topic": "world",
    "lean": null,
    "confidence": 0.4,
    "leanRationale": "Discovered via dataset; lean assigned per item by analysis (not source-level).",
    "lang": "ka"
  },
  {
    "id": "ge-georgiasentinelnews-com",
    "title": "georgiasentinelnews.com",
    "url": "https://www.georgiasentinelnews.com/feed/",
    "kind": "news",
    "topic": "world",
    "lean": null,
    "confidence": 0.4,
    "leanRationale": "Discovered via dataset; lean assigned per item by analysis (not source-level).",
    "lang": "ka"
  },
  {
    "id": "ge-thegeorgeanne-com",
    "title": "thegeorgeanne.com",
    "url": "https://thegeorgeanne.com/feed/",
    "kind": "news",
    "topic": "world",
    "lean": null,
    "confidence": 0.4,
    "leanRationale": "Discovered via dataset; lean assigned per item by analysis (not source-level).",
    "lang": "ka"
  },
  {
    "id": "ge-thecrier-net",
    "title": "thecrier.net",
    "url": "https://www.thecrier.net/feed",
    "kind": "news",
    "topic": "world",
    "lean": null,
    "confidence": 0.4,
    "leanRationale": "Discovered via dataset; lean assigned per item by analysis (not source-level).",
    "lang": "ka"
  },
  {
    "id": "ge-elnuevogeorgia-com",
    "title": "elnuevogeorgia.com",
    "url": "https://elnuevogeorgia.com/feed/",
    "kind": "news",
    "topic": "world",
    "lean": null,
    "confidence": 0.4,
    "leanRationale": "Discovered via dataset; lean assigned per item by analysis (not source-level).",
    "lang": "ka"
  },
  {
    "id": "ge-baxleynewsbanner-com",
    "title": "baxleynewsbanner.com",
    "url": "https://www.baxleynewsbanner.com/feed/",
    "kind": "news",
    "topic": "world",
    "lean": null,
    "confidence": 0.4,
    "leanRationale": "Discovered via dataset; lean assigned per item by analysis (not source-level).",
    "lang": "ka"
  },
  {
    "id": "ge-cairomessenger-com",
    "title": "cairomessenger.com",
    "url": "https://www.cairomessenger.com/feed/",
    "kind": "news",
    "topic": "world",
    "lean": null,
    "confidence": 0.4,
    "leanRationale": "Discovered via dataset; lean assigned per item by analysis (not source-level).",
    "lang": "ka"
  },
  {
    "id": "ge-gwinnettcitizen-com",
    "title": "gwinnettcitizen.com",
    "url": "https://gwinnettcitizen.com/feed/",
    "kind": "news",
    "topic": "world",
    "lean": null,
    "confidence": 0.4,
    "leanRationale": "Discovered via dataset; lean assigned per item by analysis (not source-level).",
    "lang": "ka"
  },
  {
    "id": "ge-flagpole-com",
    "title": "flagpole.com",
    "url": "https://flagpole.com/feed/",
    "kind": "news",
    "topic": "world",
    "lean": null,
    "confidence": 0.4,
    "leanRationale": "Discovered via dataset; lean assigned per item by analysis (not source-level).",
    "lang": "ka"
  },
  {
    "id": "ge-henrycountytimes-com",
    "title": "henrycountytimes.com",
    "url": "https://www.henrycountytimes.com/feed/",
    "kind": "news",
    "topic": "world",
    "lean": null,
    "confidence": 0.4,
    "leanRationale": "Discovered via dataset; lean assigned per item by analysis (not source-level).",
    "lang": "ka"
  },
  {
    "id": "ge-news-reporter-com",
    "title": "news-reporter.com",
    "url": "https://www.news-reporter.com/feed/",
    "kind": "news",
    "topic": "world",
    "lean": null,
    "confidence": 0.4,
    "leanRationale": "Discovered via dataset; lean assigned per item by analysis (not source-level).",
    "lang": "ka"
  },
  {
    "id": "ge-theberrienpress-com",
    "title": "theberrienpress.com",
    "url": "https://www.theberrienpress.com/feed/",
    "kind": "news",
    "topic": "world",
    "lean": null,
    "confidence": 0.4,
    "leanRationale": "Discovered via dataset; lean assigned per item by analysis (not source-level).",
    "lang": "ka"
  },
  {
    "id": "ge-thesummervillenews-com",
    "title": "thesummervillenews.com",
    "url": "https://www.thesummervillenews.com/feed/",
    "kind": "news",
    "topic": "world",
    "lean": null,
    "confidence": 0.4,
    "leanRationale": "Discovered via dataset; lean assigned per item by analysis (not source-level).",
    "lang": "ka"
  },
  {
    "id": "ge-newsandviewsusa-com",
    "title": "newsandviewsusa.com",
    "url": "http://newsandviewsusa.com/feed/",
    "kind": "news",
    "topic": "world",
    "lean": null,
    "confidence": 0.4,
    "leanRationale": "Discovered via dataset; lean assigned per item by analysis (not source-level).",
    "lang": "ka"
  },
  {
    "id": "ge-wsav-com",
    "title": "wsav.com",
    "url": "http://wsav.com/feed",
    "kind": "news",
    "topic": "world",
    "lean": null,
    "confidence": 0.4,
    "leanRationale": "Discovered via dataset; lean assigned per item by analysis (not source-level).",
    "lang": "ka"
  },
  {
    "id": "ge-buckheadview-com",
    "title": "buckheadview.com",
    "url": "https://simplybuckhead.com/feed/",
    "kind": "news",
    "topic": "world",
    "lean": null,
    "confidence": 0.4,
    "leanRationale": "Discovered via dataset; lean assigned per item by analysis (not source-level).",
    "lang": "ka"
  },
  {
    "id": "ge-wrbl-com",
    "title": "wrbl.com",
    "url": "http://wrbl.com/feed",
    "kind": "news",
    "topic": "world",
    "lean": null,
    "confidence": 0.4,
    "leanRationale": "Discovered via dataset; lean assigned per item by analysis (not source-level).",
    "lang": "ka"
  },
  {
    "id": "ge-thewestgeorgian-com",
    "title": "thewestgeorgian.com",
    "url": "https://thewestgeorgian.com/feed/",
    "kind": "news",
    "topic": "world",
    "lean": null,
    "confidence": 0.4,
    "leanRationale": "Discovered via dataset; lean assigned per item by analysis (not source-level).",
    "lang": "ka"
  },
  {
    "id": "ge-lakesidenews-com",
    "title": "lakesidenews.com",
    "url": "https://lakesidenews.com/feed/",
    "kind": "news",
    "topic": "world",
    "lean": null,
    "confidence": 0.4,
    "leanRationale": "Discovered via dataset; lean assigned per item by analysis (not source-level).",
    "lang": "ka"
  },
  {
    "id": "ge-fun101fm-blogspot-ca",
    "title": "fun101fm.blogspot.ca",
    "url": "http://fun101fm.blogspot.com/feeds/posts/default",
    "kind": "news",
    "topic": "world",
    "lean": null,
    "confidence": 0.4,
    "leanRationale": "Discovered via dataset; lean assigned per item by analysis (not source-level).",
    "lang": "ka"
  },
  {
    "id": "ge-wswg-tv",
    "title": "wswg.tv",
    "url": "https://www.southgatv.com/feed/",
    "kind": "news",
    "topic": "world",
    "lean": null,
    "confidence": 0.4,
    "leanRationale": "Discovered via dataset; lean assigned per item by analysis (not source-level).",
    "lang": "ka"
  },
  {
    "id": "ge-news-ge",
    "title": "news.ge",
    "url": "https://news.ge/feed/",
    "kind": "news",
    "topic": "world",
    "lean": null,
    "confidence": 0.4,
    "leanRationale": "Discovered via dataset; lean assigned per item by analysis (not source-level).",
    "lang": "ka"
  },
  {
    "id": "ge-on-ge",
    "title": "on.ge",
    "url": "http://on.ge/rss",
    "kind": "news",
    "topic": "world",
    "lean": null,
    "confidence": 0.4,
    "leanRationale": "Discovered via dataset; lean assigned per item by analysis (not source-level).",
    "lang": "ka"
  },
  {
    "id": "ge-fortuna-ge",
    "title": "fortuna.ge",
    "url": "https://fortuna.ge/feed/",
    "kind": "news",
    "topic": "world",
    "lean": null,
    "confidence": 0.4,
    "leanRationale": "Discovered via dataset; lean assigned per item by analysis (not source-level).",
    "lang": "ka"
  },
  {
    "id": "ge-megatv-ge",
    "title": "megatv.ge",
    "url": "https://megatv.ge/feed/",
    "kind": "news",
    "topic": "world",
    "lean": null,
    "confidence": 0.4,
    "leanRationale": "Discovered via dataset; lean assigned per item by analysis (not source-level).",
    "lang": "ka"
  },
  {
    "id": "ge-publika-ge",
    "title": "publika.ge",
    "url": "http://publika.ge/feed",
    "kind": "news",
    "topic": "world",
    "lean": null,
    "confidence": 0.4,
    "leanRationale": "Discovered via dataset; lean assigned per item by analysis (not source-level).",
    "lang": "ka"
  },
  {
    "id": "ge-oc-media-org",
    "title": "oc-media.org",
    "url": "https://oc-media.org/feed/",
    "kind": "news",
    "topic": "world",
    "lean": null,
    "confidence": 0.4,
    "leanRationale": "Discovered via dataset; lean assigned per item by analysis (not source-level).",
    "lang": "ka"
  },
  {
    "id": "ge-newsgeorgia-ge",
    "title": "newsgeorgia.ge",
    "url": "https://www.newsgeorgia.ge/feed/",
    "kind": "news",
    "topic": "world",
    "lean": null,
    "confidence": 0.4,
    "leanRationale": "Discovered via dataset; lean assigned per item by analysis (not source-level).",
    "lang": "ka"
  },
  {
    "id": "ge-jam-news-net",
    "title": "jam-news.net",
    "url": "http://jam-news.net/feed",
    "kind": "news",
    "topic": "world",
    "lean": null,
    "confidence": 0.4,
    "leanRationale": "Discovered via dataset; lean assigned per item by analysis (not source-level).",
    "lang": "ka"
  },
  {
    "id": "ge-gazeta-ra-info",
    "title": "gazeta-ra.info",
    "url": "http://www.gazeta-ra.info/?format=feed",
    "kind": "news",
    "topic": "world",
    "lean": null,
    "confidence": 0.4,
    "leanRationale": "Discovered via dataset; lean assigned per item by analysis (not source-level).",
    "lang": "ka"
  },
  {
    "id": "ge-finchannel-com",
    "title": "finchannel.com",
    "url": "https://finchannel.com/feed/",
    "kind": "news",
    "topic": "world",
    "lean": null,
    "confidence": 0.4,
    "leanRationale": "Discovered via dataset; lean assigned per item by analysis (not source-level).",
    "lang": "ka"
  },
  {
    "id": "ge-abkhazeti-info",
    "title": "abkhazeti.info",
    "url": "https://www.abkhazeti.info/feed/",
    "kind": "news",
    "topic": "world",
    "lean": null,
    "confidence": 0.4,
    "leanRationale": "Discovered via dataset; lean assigned per item by analysis (not source-level).",
    "lang": "ka"
  },
  {
    "id": "ge-ifact-ge",
    "title": "ifact.ge",
    "url": "http://ifact.ge/rss",
    "kind": "news",
    "topic": "world",
    "lean": null,
    "confidence": 0.4,
    "leanRationale": "Discovered via dataset; lean assigned per item by analysis (not source-level).",
    "lang": "ka"
  },
  {
    "id": "ge-kvirispalitra-ge",
    "title": "kvirispalitra.ge",
    "url": "http://www.kvirispalitra.ge/atom.xml",
    "kind": "news",
    "topic": "world",
    "lean": null,
    "confidence": 0.4,
    "leanRationale": "Discovered via dataset; lean assigned per item by analysis (not source-level).",
    "lang": "ka"
  },
  {
    "id": "ge-georgianjournal-ge",
    "title": "georgianjournal.ge",
    "url": "http://georgianjournal.ge/atom.xml",
    "kind": "news",
    "topic": "world",
    "lean": null,
    "confidence": 0.4,
    "leanRationale": "Discovered via dataset; lean assigned per item by analysis (not source-level).",
    "lang": "ka"
  },
  {
    "id": "ge-kavkasiatv-ge",
    "title": "kavkasiatv.ge",
    "url": "https://kavkasiatv.ge/feed/",
    "kind": "news",
    "topic": "world",
    "lean": null,
    "confidence": 0.4,
    "leanRationale": "Discovered via dataset; lean assigned per item by analysis (not source-level).",
    "lang": "ka"
  },
  {
    "id": "ge-netgazeti-ge",
    "title": "netgazeti.ge",
    "url": "https://netgazeti.ge/feed/",
    "kind": "news",
    "topic": "world",
    "lean": null,
    "confidence": 0.4,
    "leanRationale": "Discovered via dataset; lean assigned per item by analysis (not source-level).",
    "lang": "ka"
  },
  {
    "id": "ge-rionitv-com",
    "title": "rionitv.com",
    "url": "http://www.rionitv.com/engine/rss.php",
    "kind": "news",
    "topic": "world",
    "lean": null,
    "confidence": 0.4,
    "leanRationale": "Discovered via dataset; lean assigned per item by analysis (not source-level).",
    "lang": "ka"
  },
  {
    "id": "ge-knews-ge",
    "title": "knews.ge",
    "url": "https://knews.ge/?feed=rss2",
    "kind": "news",
    "topic": "world",
    "lean": null,
    "confidence": 0.4,
    "leanRationale": "Discovered via dataset; lean assigned per item by analysis (not source-level).",
    "lang": "ka"
  },
  {
    "id": "ge-asavali-ge",
    "title": "asavali.ge",
    "url": "https://asavali.com/feed/",
    "kind": "news",
    "topic": "world",
    "lean": null,
    "confidence": 0.4,
    "leanRationale": "Discovered via dataset; lean assigned per item by analysis (not source-level).",
    "lang": "ka"
  },
  {
    "id": "ge-sova-news",
    "title": "sova.news",
    "url": "https://sova.news/feed/",
    "kind": "news",
    "topic": "world",
    "lean": null,
    "confidence": 0.4,
    "leanRationale": "Discovered via dataset; lean assigned per item by analysis (not source-level).",
    "lang": "ka"
  },
  {
    "id": "ge-monitori-ge",
    "title": "monitori.ge",
    "url": "http://monitori.ge/feed",
    "kind": "news",
    "topic": "world",
    "lean": null,
    "confidence": 0.4,
    "leanRationale": "Discovered via dataset; lean assigned per item by analysis (not source-level).",
    "lang": "ka"
  },
  {
    "id": "ge-svobodnaya-info",
    "title": "svobodnaya.info",
    "url": "http://svobodnaya.info/ru/?format=feed&amp;type=rss",
    "kind": "news",
    "topic": "world",
    "lean": null,
    "confidence": 0.4,
    "leanRationale": "Discovered via dataset; lean assigned per item by analysis (not source-level).",
    "lang": "ka"
  },
  {
    "id": "ge-tavisupleba-org",
    "title": "tavisupleba.org",
    "url": "http://tavisupleba.org/api/",
    "kind": "news",
    "topic": "world",
    "lean": null,
    "confidence": 0.4,
    "leanRationale": "Discovered via dataset; lean assigned per item by analysis (not source-level).",
    "lang": "ka"
  },
  {
    "id": "ge-messenger-com-ge",
    "title": "messenger.com.ge",
    "url": "http://www.messenger.com.ge/rss.xml",
    "kind": "news",
    "topic": "world",
    "lean": null,
    "confidence": 0.4,
    "leanRationale": "Discovered via dataset; lean assigned per item by analysis (not source-level).",
    "lang": "ka"
  },
  {
    "id": "ge-forset-ge",
    "title": "forset.ge",
    "url": "https://www.forset.ge/blog-feed.xml",
    "kind": "news",
    "topic": "world",
    "lean": null,
    "confidence": 0.4,
    "leanRationale": "Discovered via dataset; lean assigned per item by analysis (not source-level).",
    "lang": "ka"
  },
  {
    "id": "ge-tvkvemokartli-ge",
    "title": "tvkvemokartli.ge",
    "url": "https://tv4.ge/feed/",
    "kind": "news",
    "topic": "world",
    "lean": null,
    "confidence": 0.4,
    "leanRationale": "Discovered via dataset; lean assigned per item by analysis (not source-level).",
    "lang": "ka"
  }
]
