[
  {
    "id": "ug-the-observer",
    "title": "The Observer",
    "url": "https://observer.ug/feed/",
    "kind": "news",
    "topic": "world",
    "lean": null,
    "confidence": 0.4,
    "leanRationale": "Discovered via dataset; lean assigned per item by analysis (not source-level).",
    "lang": "sw",
    "region": "UG-C",
    "regionLabel": "Mkoa wa Kati"
  },
  {
    "id": "ug-the-independent-magazine",
    "title": "The Independent magazine",
    "url": "http://www.independent.co.ug/feed",
    "kind": "news",
    "topic": "world",
    "lean": null,
    "confidence": 0.4,
    "leanRationale": "Discovered via dataset; lean assigned per item by analysis (not source-level).",
    "lang": "sw"
  },
  {
    "id": "ug-ntv-uganda",
    "title": "NTV Uganda",
    "url": "https://ntv.co.ug/feed",
    "kind": "news",
    "topic": "world",
    "lean": null,
    "confidence": 0.4,
    "leanRationale": "Discovered via dataset; lean assigned per item by analysis (not source-level).",
    "lang": "sw"
  },
  {
    "id": "ug-kfm",
    "title": "Kfm",
    "url": "https://www.kfm.co.ug/feed/",
    "kind": "news",
    "topic": "world",
    "lean": null,
    "confidence": 0.4,
    "leanRationale": "Discovered via dataset; lean assigned per item by analysis (not source-level).",
    "lang": "sw"
  },
  {
    "id": "ug-100-2-galaxy-fm",
    "title": "100.2 Galaxy FM",
    "url": "https://www.galaxyfm.co.ug/feed",
    "kind": "news",
    "topic": "world",
    "lean": null,
    "confidence": 0.4,
    "leanRationale": "Discovered via dataset; lean assigned per item by analysis (not source-level).",
    "lang": "sw"
  },
  {
    "id": "ug-88-2-sanyu-fm",
    "title": "88.2 Sanyu FM",
    "url": "https://sanyufm.com/feed/",
    "kind": "news",
    "topic": "world",
    "lean": null,
    "confidence": 0.4,
    "leanRationale": "Discovered via dataset; lean assigned per item by analysis (not source-level).",
    "lang": "sw"
  },
  {
    "id": "ug-radio-sapientia-94-4-fm",
    "title": "Radio Sapientia 94.4 FM",
    "url": "https://www.radiosapientia.com/feed/",
    "kind": "news",
    "topic": "world",
    "lean": null,
    "confidence": 0.4,
    "leanRationale": "Discovered via dataset; lean assigned per item by analysis (not source-level).",
    "lang": "sw",
    "region": "UG-C",
    "regionLabel": "Mkoa wa Kati"
  },
  {
    "id": "ug-monitor-co-ug",
    "title": "monitor.co.ug",
    "url": "http://www.monitor.co.ug/rss.xml",
    "kind": "news",
    "topic": "world",
    "lean": null,
    "confidence": 0.4,
    "leanRationale": "Discovered via dataset; lean assigned per item by analysis (not source-level).",
    "lang": "sw"
  },
  {
    "id": "ug-watchdoguganda-com",
    "title": "watchdoguganda.com",
    "url": "https://www.watchdoguganda.com/feed",
    "kind": "news",
    "topic": "world",
    "lean": null,
    "confidence": 0.4,
    "leanRationale": "Discovered via dataset; lean assigned per item by analysis (not source-level).",
    "lang": "sw"
  },
  {
    "id": "ug-pctechmag-com",
    "title": "pctechmag.com",
    "url": "https://pctechmag.com/feed/",
    "kind": "news",
    "topic": "world",
    "lean": null,
    "confidence": 0.4,
    "leanRationale": "Discovered via dataset; lean assigned per item by analysis (not source-level).",
    "lang": "sw"
  },
  {
    "id": "ug-kawowo-com",
    "title": "kawowo.com",
    "url": "https://kawowo.com/feed/",
    "kind": "news",
    "topic": "world",
    "lean": null,
    "confidence": 0.4,
    "leanRationale": "Discovered via dataset; lean assigned per item by analysis (not source-level).",
    "lang": "sw"
  },
  {
    "id": "ug-mulengeranews-com",
    "title": "mulengeranews.com",
    "url": "https://mulengeranews.com/feed/",
    "kind": "news",
    "topic": "world",
    "lean": null,
    "confidence": 0.4,
    "leanRationale": "Discovered via dataset; lean assigned per item by analysis (not source-level).",
    "lang": "sw"
  },
  {
    "id": "ug-redpepper-co-ug",
    "title": "redpepper.co.ug",
    "url": "https://redpepper.co.ug/feed/",
    "kind": "news",
    "topic": "world",
    "lean": null,
    "confidence": 0.4,
    "leanRationale": "Discovered via dataset; lean assigned per item by analysis (not source-level).",
    "lang": "sw"
  },
  {
    "id": "ug-matookerepublic-com",
    "title": "matookerepublic.com",
    "url": "https://www.matookerepublic.com/feed/",
    "kind": "news",
    "topic": "world",
    "lean": null,
    "confidence": 0.4,
    "leanRationale": "Discovered via dataset; lean assigned per item by analysis (not source-level).",
    "lang": "sw"
  },
  {
    "id": "ug-softpower-ug",
    "title": "softpower.ug",
    "url": "https://softpower.ug/feed/",
    "kind": "news",
    "topic": "world",
    "lean": null,
    "confidence": 0.4,
    "leanRationale": "Discovered via dataset; lean assigned per item by analysis (not source-level).",
    "lang": "sw"
  },
  {
    "id": "ug-sqoop-co-ug",
    "title": "sqoop.co.ug",
    "url": "https://www.sqoop.co.ug/feed",
    "kind": "news",
    "topic": "world",
    "lean": null,
    "confidence": 0.4,
    "leanRationale": "Discovered via dataset; lean assigned per item by analysis (not source-level).",
    "lang": "sw"
  },
  {
    "id": "ug-ugandaradionetwork-com",
    "title": "ugandaradionetwork.com",
    "url": "https://ugandaradionetwork.com/s/feed/",
    "kind": "news",
    "topic": "world",
    "lean": null,
    "confidence": 0.4,
    "leanRationale": "Discovered via dataset; lean assigned per item by analysis (not source-level).",
    "lang": "sw"
  },
  {
    "id": "ug-eagle-co-ug",
    "title": "eagle.co.ug",
    "url": "https://eagle.co.ug/feed/",
    "kind": "news",
    "topic": "world",
    "lean": null,
    "confidence": 0.4,
    "leanRationale": "Discovered via dataset; lean assigned per item by analysis (not source-level).",
    "lang": "sw"
  },
  {
    "id": "ug-spyuganda-com",
    "title": "spyuganda.com",
    "url": "https://www.spyuganda.com/feed/",
    "kind": "news",
    "topic": "world",
    "lean": null,
    "confidence": 0.4,
    "leanRationale": "Discovered via dataset; lean assigned per item by analysis (not source-level).",
    "lang": "sw"
  },
  {
    "id": "ug-radiosimba-ug",
    "title": "radiosimba.ug",
    "url": "https://www.radiosimba.ug/feed",
    "kind": "news",
    "topic": "world",
    "lean": null,
    "confidence": 0.4,
    "leanRationale": "Discovered via dataset; lean assigned per item by analysis (not source-level).",
    "lang": "sw"
  },
  {
    "id": "ug-newslexpoint-com",
    "title": "newslexpoint.com",
    "url": "https://newslexpoint.com/feed/",
    "kind": "news",
    "topic": "world",
    "lean": null,
    "confidence": 0.4,
    "leanRationale": "Discovered via dataset; lean assigned per item by analysis (not source-level).",
    "lang": "sw"
  },
  {
    "id": "ug-theinsider-ug",
    "title": "theinsider.ug",
    "url": "https://theinsider.ug/index.php/feed/",
    "kind": "news",
    "topic": "world",
    "lean": null,
    "confidence": 0.4,
    "leanRationale": "Discovered via dataset; lean assigned per item by analysis (not source-level).",
    "lang": "sw"
  },
  {
    "id": "ug-256businessnews-com",
    "title": "256businessnews.com",
    "url": "https://www.256businessnews.com/feed",
    "kind": "news",
    "topic": "world",
    "lean": null,
    "confidence": 0.4,
    "leanRationale": "Discovered via dataset; lean assigned per item by analysis (not source-level).",
    "lang": "sw"
  },
  {
    "id": "ug-dailypost-ug",
    "title": "dailypost.ug",
    "url": "http://dailypost.ug/feed",
    "kind": "news",
    "topic": "world",
    "lean": null,
    "confidence": 0.4,
    "leanRationale": "Discovered via dataset; lean assigned per item by analysis (not source-level).",
    "lang": "sw"
  },
  {
    "id": "ug-infonile-org",
    "title": "infonile.org",
    "url": "https://infonile.org/feed",
    "kind": "news",
    "topic": "world",
    "lean": null,
    "confidence": 0.4,
    "leanRationale": "Discovered via dataset; lean assigned per item by analysis (not source-level).",
    "lang": "sw"
  },
  {
    "id": "ug-trumpetnews-co-ug",
    "title": "trumpetnews.co.ug",
    "url": "https://trumpetnews.co.ug/feed/",
    "kind": "news",
    "topic": "world",
    "lean": null,
    "confidence": 0.4,
    "leanRationale": "Discovered via dataset; lean assigned per item by analysis (not source-level).",
    "lang": "sw"
  },
  {
    "id": "ug-dembefm-ug",
    "title": "dembefm.ug",
    "url": "https://dembefm.ug/feed",
    "kind": "news",
    "topic": "world",
    "lean": null,
    "confidence": 0.4,
    "leanRationale": "Discovered via dataset; lean assigned per item by analysis (not source-level).",
    "lang": "sw"
  },
  {
    "id": "ug-ugbusiness-com",
    "title": "ugbusiness.com",
    "url": "https://ugbusiness.com/feed",
    "kind": "news",
    "topic": "world",
    "lean": null,
    "confidence": 0.4,
    "leanRationale": "Discovered via dataset; lean assigned per item by analysis (not source-level).",
    "lang": "sw"
  },
  {
    "id": "ug-nbs-ug",
    "title": "nbs.ug",
    "url": "https://nbs.ug/feed/",
    "kind": "news",
    "topic": "world",
    "lean": null,
    "confidence": 0.4,
    "leanRationale": "Discovered via dataset; lean assigned per item by analysis (not source-level).",
    "lang": "sw"
  },
  {
    "id": "ug-acholitimes-com",
    "title": "acholitimes.com",
    "url": "http://www.acholitimes.com/feed/",
    "kind": "news",
    "topic": "world",
    "lean": null,
    "confidence": 0.4,
    "leanRationale": "Discovered via dataset; lean assigned per item by analysis (not source-level).",
    "lang": "sw"
  },
  {
    "id": "ug-theinvestigatornews-com",
    "title": "theinvestigatornews.com",
    "url": "https://theinvestigatornews.com/feed/",
    "kind": "news",
    "topic": "world",
    "lean": null,
    "confidence": 0.4,
    "leanRationale": "Discovered via dataset; lean assigned per item by analysis (not source-level).",
    "lang": "sw"
  },
  {
    "id": "ug-radioonefm90-com",
    "title": "radioonefm90.com",
    "url": "https://radioonefm90.com/feed/",
    "kind": "news",
    "topic": "world",
    "lean": null,
    "confidence": 0.4,
    "leanRationale": "Discovered via dataset; lean assigned per item by analysis (not source-level).",
    "lang": "sw"
  },
  {
    "id": "ug-radiowa-org",
    "title": "radiowa.org",
    "url": "https://radiowa.org/feed/",
    "kind": "news",
    "topic": "world",
    "lean": null,
    "confidence": 0.4,
    "leanRationale": "Discovered via dataset; lean assigned per item by analysis (not source-level).",
    "lang": "sw"
  },
  {
    "id": "ug-dispatch-ug",
    "title": "dispatch.ug",
    "url": "https://www.dispatch.ug/feed/",
    "kind": "news",
    "topic": "world",
    "lean": null,
    "confidence": 0.4,
    "leanRationale": "Discovered via dataset; lean assigned per item by analysis (not source-level).",
    "lang": "sw"
  },
  {
    "id": "ug-thegrapevine-co-ug",
    "title": "thegrapevine.co.ug",
    "url": "https://www.thegrapevine.co.ug/feed/",
    "kind": "news",
    "topic": "world",
    "lean": null,
    "confidence": 0.4,
    "leanRationale": "Discovered via dataset; lean assigned per item by analysis (not source-level).",
    "lang": "sw"
  }
]
