[
  {
    "id": "za-metro-fm",
    "title": "Metro FM",
    "url": "https://www.metrofm.co.za/metro-fm/feed/",
    "kind": "news",
    "topic": "world",
    "lean": null,
    "confidence": 0.4,
    "leanRationale": "Discovered via dataset; lean assigned per item by analysis (not source-level).",
    "lang": "nr"
  },
  {
    "id": "za-bush-radio",
    "title": "Bush Radio",
    "url": "https://bushradio.wordpress.com/feed/",
    "kind": "news",
    "topic": "world",
    "lean": null,
    "confidence": 0.4,
    "leanRationale": "Discovered via dataset; lean assigned per item by analysis (not source-level).",
    "lang": "nr"
  },
  {
    "id": "za-radio-sonder-grense",
    "title": "Radio Sonder Grense",
    "url": "https://www.rsg.co.za/rsg-fm/feed/",
    "kind": "news",
    "topic": "world",
    "lean": null,
    "confidence": 0.4,
    "leanRationale": "Discovered via dataset; lean assigned per item by analysis (not source-level).",
    "lang": "nr"
  },
  {
    "id": "za-channel-africa",
    "title": "Channel Africa",
    "url": "https://www.channelafrica.co.za/channelafrica/feed/",
    "kind": "news",
    "topic": "world",
    "lean": null,
    "confidence": 0.4,
    "leanRationale": "Discovered via dataset; lean assigned per item by analysis (not source-level).",
    "lang": "nr"
  },
  {
    "id": "za-mfm-92-6",
    "title": "MFM 92.6",
    "url": "http://mfm.co.za/feed/",
    "kind": "news",
    "topic": "world",
    "lean": null,
    "confidence": 0.4,
    "leanRationale": "Discovered via dataset; lean assigned per item by analysis (not source-level).",
    "lang": "nr"
  },
  {
    "id": "za-cape-argus",
    "title": "Cape Argus",
    "url": "http://www.capeargus.co.za/rss/",
    "kind": "news",
    "topic": "world",
    "lean": null,
    "confidence": 0.4,
    "leanRationale": "Discovered via dataset; lean assigned per item by analysis (not source-level).",
    "lang": "nr"
  },
  {
    "id": "za-isolezwe",
    "title": "Isolezwe",
    "url": "https://isolezwe.co.za/rss/",
    "kind": "news",
    "topic": "world",
    "lean": null,
    "confidence": 0.4,
    "leanRationale": "Discovered via dataset; lean assigned per item by analysis (not source-level).",
    "lang": "nr"
  },
  {
    "id": "za-sabc-1",
    "title": "SABC 1",
    "url": "https://www.sabc1.co.za/sabc1/feed/",
    "kind": "news",
    "topic": "world",
    "lean": null,
    "confidence": 0.4,
    "leanRationale": "Discovered via dataset; lean assigned per item by analysis (not source-level).",
    "lang": "nr",
    "region": "ZA-GP",
    "regionLabel": "Gauteng"
  },
  {
    "id": "za-sabc-2",
    "title": "SABC 2",
    "url": "https://www.sabc2.co.za/sabc2/feed/",
    "kind": "news",
    "topic": "world",
    "lean": null,
    "confidence": 0.4,
    "leanRationale": "Discovered via dataset; lean assigned per item by analysis (not source-level).",
    "lang": "nr",
    "region": "ZA-GP",
    "regionLabel": "Gauteng"
  },
  {
    "id": "za-sabc-3",
    "title": "SABC 3",
    "url": "https://www.sabc3.co.za/sabc3/feed/",
    "kind": "news",
    "topic": "world",
    "lean": null,
    "confidence": 0.4,
    "leanRationale": "Discovered via dataset; lean assigned per item by analysis (not source-level).",
    "lang": "nr",
    "region": "ZA-GP",
    "regionLabel": "Gauteng"
  },
  {
    "id": "za-ukhozi-fm",
    "title": "Ukhozi FM",
    "url": "https://www.ukhozifm.co.za/ukhozifm/comments/feed/",
    "kind": "news",
    "topic": "world",
    "lean": null,
    "confidence": 0.4,
    "leanRationale": "Discovered via dataset; lean assigned per item by analysis (not source-level).",
    "lang": "nr"
  },
  {
    "id": "za-cnbc-africa",
    "title": "CNBC Africa",
    "url": "http://www.cnbcafrica.com/feed.xml",
    "kind": "news",
    "topic": "world",
    "lean": null,
    "confidence": 0.4,
    "leanRationale": "Discovered via dataset; lean assigned per item by analysis (not source-level).",
    "lang": "nr"
  },
  {
    "id": "za-business-day",
    "title": "Business Day",
    "url": "https://bdlive.co.za/feed/",
    "kind": "news",
    "topic": "world",
    "lean": null,
    "confidence": 0.4,
    "leanRationale": "Discovered via dataset; lean assigned per item by analysis (not source-level).",
    "lang": "nr",
    "region": "ZA-WC",
    "regionLabel": "Western Cape"
  },
  {
    "id": "za-independent-online",
    "title": "Independent Online",
    "url": "https://www.iol.co.za/rss/",
    "kind": "news",
    "topic": "world",
    "lean": null,
    "confidence": 0.4,
    "leanRationale": "Discovered via dataset; lean assigned per item by analysis (not source-level).",
    "lang": "nr"
  },
  {
    "id": "za-daily-maverick",
    "title": "Daily Maverick",
    "url": "https://www.dailymaverick.co.za/rss",
    "kind": "news",
    "topic": "world",
    "lean": null,
    "confidence": 0.4,
    "leanRationale": "Discovered via dataset; lean assigned per item by analysis (not source-level).",
    "lang": "nr",
    "region": "ZA-GP",
    "regionLabel": "Gauteng"
  },
  {
    "id": "za-fine-music-radio",
    "title": "Fine Music Radio",
    "url": "https://www.fmr.co.za/comments/feed/",
    "kind": "news",
    "topic": "world",
    "lean": null,
    "confidence": 0.4,
    "leanRationale": "Discovered via dataset; lean assigned per item by analysis (not source-level).",
    "lang": "nr"
  },
  {
    "id": "za-good-hope-fm",
    "title": "Good Hope FM",
    "url": "https://www.goodhopefm.co.za/goodhopefm/feed/",
    "kind": "news",
    "topic": "world",
    "lean": null,
    "confidence": 0.4,
    "leanRationale": "Discovered via dataset; lean assigned per item by analysis (not source-level).",
    "lang": "nr"
  },
  {
    "id": "za-heart-104-9-fm",
    "title": "Heart 104.9 FM",
    "url": "https://www.heartfm.co.za/feed/",
    "kind": "news",
    "topic": "world",
    "lean": null,
    "confidence": 0.4,
    "leanRationale": "Discovered via dataset; lean assigned per item by analysis (not source-level).",
    "lang": "nr"
  },
  {
    "id": "za-jozi-fm",
    "title": "Jozi FM",
    "url": "http://www.jozifm.co.za/feed",
    "kind": "news",
    "topic": "world",
    "lean": null,
    "confidence": 0.4,
    "leanRationale": "Discovered via dataset; lean assigned per item by analysis (not source-level).",
    "lang": "nr"
  },
  {
    "id": "za-kaya-fm",
    "title": "Kaya FM",
    "url": "https://www.kaya959.co.za/feed/",
    "kind": "news",
    "topic": "world",
    "lean": null,
    "confidence": 0.4,
    "leanRationale": "Discovered via dataset; lean assigned per item by analysis (not source-level).",
    "lang": "nr"
  },
  {
    "id": "za-phalaphala-fm",
    "title": "Phalaphala FM",
    "url": "https://www.phalaphalafm.co.za/phalaphalafm/feed/",
    "kind": "news",
    "topic": "world",
    "lean": null,
    "confidence": 0.4,
    "leanRationale": "Discovered via dataset; lean assigned per item by analysis (not source-level).",
    "lang": "nr"
  },
  {
    "id": "za-lesedi-fm",
    "title": "Lesedi FM",
    "url": "https://www.lesedifm.co.za/lesedifm/feed/",
    "kind": "news",
    "topic": "world",
    "lean": null,
    "confidence": 0.4,
    "leanRationale": "Discovered via dataset; lean assigned per item by analysis (not source-level).",
    "lang": "nr"
  },
  {
    "id": "za-lotus-fm",
    "title": "Lotus FM",
    "url": "https://www.lotusfm.co.za/lotusfm/feed/",
    "kind": "news",
    "topic": "world",
    "lean": null,
    "confidence": 0.4,
    "leanRationale": "Discovered via dataset; lean assigned per item by analysis (not source-level).",
    "lang": "nr"
  },
  {
    "id": "za-munghana-lonene-fm",
    "title": "Munghana Lonene FM",
    "url": "https://www.munghanalonenefm.co.za/munghanalonenefm/feed/",
    "kind": "news",
    "topic": "world",
    "lean": null,
    "confidence": 0.4,
    "leanRationale": "Discovered via dataset; lean assigned per item by analysis (not source-level).",
    "lang": "nr",
    "region": "ZA-LP",
    "regionLabel": "Limpopo"
  },
  {
    "id": "za-radio-2000",
    "title": "Radio 2000",
    "url": "http://radio2000.co.za/?feed=rss2",
    "kind": "news",
    "topic": "world",
    "lean": null,
    "confidence": 0.4,
    "leanRationale": "Discovered via dataset; lean assigned per item by analysis (not source-level).",
    "lang": "nr"
  },
  {
    "id": "za-the-independent-on-saturday",
    "title": "The Independent on Saturday",
    "url": "http://www.independentonsaturday.co.za/rss/",
    "kind": "news",
    "topic": "world",
    "lean": null,
    "confidence": 0.4,
    "leanRationale": "Discovered via dataset; lean assigned per item by analysis (not source-level).",
    "lang": "nr"
  },
  {
    "id": "za-boervolk-radio",
    "title": "Boervolk Radio",
    "url": "https://www.boervolkradio.co.za/feed/",
    "kind": "news",
    "topic": "world",
    "lean": null,
    "confidence": 0.4,
    "leanRationale": "Discovered via dataset; lean assigned per item by analysis (not source-level).",
    "lang": "nr"
  },
  {
    "id": "za-radiokansel-radio-pulpit",
    "title": "Radiokansel / Radio Pulpit",
    "url": "https://www.radiokansel.co.za/feed/",
    "kind": "news",
    "topic": "world",
    "lean": null,
    "confidence": 0.4,
    "leanRationale": "Discovered via dataset; lean assigned per item by analysis (not source-level).",
    "lang": "nr"
  },
  {
    "id": "za-umrhatjho-ikwekwezi",
    "title": "Umrhatjho ikwekwezi",
    "url": "https://www.ikwekwezifm.co.za/ikwekwezifm/feed/",
    "kind": "news",
    "topic": "world",
    "lean": null,
    "confidence": 0.4,
    "leanRationale": "Discovered via dataset; lean assigned per item by analysis (not source-level).",
    "lang": "nr"
  },
  {
    "id": "za-ligwalagwala-fm",
    "title": "Ligwalagwala FM",
    "url": "https://www.ligwalagwalafm.co.za/ligwalagwalafm/feed/",
    "kind": "news",
    "topic": "world",
    "lean": null,
    "confidence": 0.4,
    "leanRationale": "Discovered via dataset; lean assigned per item by analysis (not source-level).",
    "lang": "nr"
  },
  {
    "id": "za-mpowerfm",
    "title": "MPowerFM",
    "url": "http://www.mpowerfm.co.za/feed",
    "kind": "news",
    "topic": "world",
    "lean": null,
    "confidence": 0.4,
    "leanRationale": "Discovered via dataset; lean assigned per item by analysis (not source-level).",
    "lang": "nr"
  },
  {
    "id": "za-power-fm",
    "title": "Power FM",
    "url": "https://power987.co.za/feed/",
    "kind": "news",
    "topic": "world",
    "lean": null,
    "confidence": 0.4,
    "leanRationale": "Discovered via dataset; lean assigned per item by analysis (not source-level).",
    "lang": "nr"
  },
  {
    "id": "za-thobela-fm",
    "title": "Thobela FM",
    "url": "https://www.thobelafm.co.za/thobelafm/feed/",
    "kind": "news",
    "topic": "world",
    "lean": null,
    "confidence": 0.4,
    "leanRationale": "Discovered via dataset; lean assigned per item by analysis (not source-level).",
    "lang": "nr"
  },
  {
    "id": "za-tru-fm",
    "title": "Tru fm",
    "url": "https://www.trufm.co.za/trufm/feed/",
    "kind": "news",
    "topic": "world",
    "lean": null,
    "confidence": 0.4,
    "leanRationale": "Discovered via dataset; lean assigned per item by analysis (not source-level).",
    "lang": "nr"
  },
  {
    "id": "za-tuks-fm",
    "title": "Tuks FM",
    "url": "https://www.tuksfm.co.za/feed/",
    "kind": "news",
    "topic": "world",
    "lean": null,
    "confidence": 0.4,
    "leanRationale": "Discovered via dataset; lean assigned per item by analysis (not source-level).",
    "lang": "nr"
  },
  {
    "id": "za-maroela-media",
    "title": "Maroela Media",
    "url": "https://maroelamedia.co.za/feed/",
    "kind": "news",
    "topic": "world",
    "lean": null,
    "confidence": 0.4,
    "leanRationale": "Discovered via dataset; lean assigned per item by analysis (not source-level).",
    "lang": "nr",
    "region": "ZA-GP",
    "regionLabel": "Gauteng"
  },
  {
    "id": "za-african-news-agency",
    "title": "African News Agency",
    "url": "https://africannewsagency.com/feed/",
    "kind": "news",
    "topic": "world",
    "lean": null,
    "confidence": 0.4,
    "leanRationale": "Discovered via dataset; lean assigned per item by analysis (not source-level).",
    "lang": "nr",
    "region": "ZA-WC",
    "regionLabel": "Western Cape"
  },
  {
    "id": "za-eextra",
    "title": "eExtra",
    "url": "https://www.etv.co.za/rss.xml",
    "kind": "news",
    "topic": "world",
    "lean": null,
    "confidence": 0.4,
    "leanRationale": "Discovered via dataset; lean assigned per item by analysis (not source-level).",
    "lang": "nr"
  },
  {
    "id": "za-the-african-mirror",
    "title": "The African Mirror",
    "url": "https://theafricanmirror.africa/feed/",
    "kind": "news",
    "topic": "world",
    "lean": null,
    "confidence": 0.4,
    "leanRationale": "Discovered via dataset; lean assigned per item by analysis (not source-level).",
    "lang": "nr"
  },
  {
    "id": "za-ebnewsdaily",
    "title": "EBNewsDaily",
    "url": "https://www.ebnewsdaily.co.za/feed/",
    "kind": "news",
    "topic": "world",
    "lean": null,
    "confidence": 0.4,
    "leanRationale": "Discovered via dataset; lean assigned per item by analysis (not source-level).",
    "lang": "nr"
  },
  {
    "id": "za-briefly-co-za",
    "title": "briefly.co.za",
    "url": "https://briefly.co.za/rss/all.rss",
    "kind": "news",
    "topic": "world",
    "lean": null,
    "confidence": 0.4,
    "leanRationale": "Discovered via dataset; lean assigned per item by analysis (not source-level).",
    "lang": "nr"
  },
  {
    "id": "za-southafricatoday-net",
    "title": "southafricatoday.net",
    "url": "https://southafricatoday.net/feed/",
    "kind": "news",
    "topic": "world",
    "lean": null,
    "confidence": 0.4,
    "leanRationale": "Discovered via dataset; lean assigned per item by analysis (not source-level).",
    "lang": "nr"
  },
  {
    "id": "za-thesouthafrican-com",
    "title": "thesouthafrican.com",
    "url": "https://www.thesouthafrican.com/feed/",
    "kind": "news",
    "topic": "world",
    "lean": null,
    "confidence": 0.4,
    "leanRationale": "Discovered via dataset; lean assigned per item by analysis (not source-level).",
    "lang": "nr"
  },
  {
    "id": "za-sundayworld-co-za",
    "title": "sundayworld.co.za",
    "url": "https://sundayworld.co.za/feed/",
    "kind": "news",
    "topic": "world",
    "lean": null,
    "confidence": 0.4,
    "leanRationale": "Discovered via dataset; lean assigned per item by analysis (not source-level).",
    "lang": "nr"
  },
  {
    "id": "za-witness-co-za",
    "title": "witness.co.za",
    "url": "http://witness.co.za/feed",
    "kind": "news",
    "topic": "world",
    "lean": null,
    "confidence": 0.4,
    "leanRationale": "Discovered via dataset; lean assigned per item by analysis (not source-level).",
    "lang": "nr"
  },
  {
    "id": "za-magic828-co-za",
    "title": "magic828.co.za",
    "url": "https://magic828.co.za/feed/",
    "kind": "news",
    "topic": "world",
    "lean": null,
    "confidence": 0.4,
    "leanRationale": "Discovered via dataset; lean assigned per item by analysis (not source-level).",
    "lang": "nr"
  },
  {
    "id": "za-rosestad-co-za",
    "title": "rosestad.co.za",
    "url": "https://www.rosestad.co.za/blog-feed.xml",
    "kind": "news",
    "topic": "world",
    "lean": null,
    "confidence": 0.4,
    "leanRationale": "Discovered via dataset; lean assigned per item by analysis (not source-level).",
    "lang": "nr"
  },
  {
    "id": "za-capetownetc-com",
    "title": "capetownetc.com",
    "url": "https://www.capetownetc.com/feed/",
    "kind": "news",
    "topic": "world",
    "lean": null,
    "confidence": 0.4,
    "leanRationale": "Discovered via dataset; lean assigned per item by analysis (not source-level).",
    "lang": "nr"
  },
  {
    "id": "za-co-za",
    "title": "co.za",
    "url": "https://mg.co.za/atom/",
    "kind": "news",
    "topic": "world",
    "lean": null,
    "confidence": 0.4,
    "leanRationale": "Discovered via dataset; lean assigned per item by analysis (not source-level).",
    "lang": "nr"
  },
  {
    "id": "za-itweb-co-za",
    "title": "itweb.co.za",
    "url": "https://www.itweb.co.za/rss",
    "kind": "news",
    "topic": "world",
    "lean": null,
    "confidence": 0.4,
    "leanRationale": "Discovered via dataset; lean assigned per item by analysis (not source-level).",
    "lang": "nr"
  },
  {
    "id": "za-dailyvoice-co-za",
    "title": "dailyvoice.co.za",
    "url": "https://www.dailyvoice.co.za/rss/",
    "kind": "news",
    "topic": "world",
    "lean": null,
    "confidence": 0.4,
    "leanRationale": "Discovered via dataset; lean assigned per item by analysis (not source-level).",
    "lang": "nr"
  },
  {
    "id": "za-dfa-co-za",
    "title": "dfa.co.za",
    "url": "https://www.dfa.co.za/rss/",
    "kind": "news",
    "topic": "world",
    "lean": null,
    "confidence": 0.4,
    "leanRationale": "Discovered via dataset; lean assigned per item by analysis (not source-level).",
    "lang": "nr"
  },
  {
    "id": "za-isolezwelesixhosa-co-za",
    "title": "isolezwelesixhosa.co.za",
    "url": "https://www.isolezwelesixhosa.co.za/rss/",
    "kind": "news",
    "topic": "world",
    "lean": null,
    "confidence": 0.4,
    "leanRationale": "Discovered via dataset; lean assigned per item by analysis (not source-level).",
    "lang": "nr"
  },
  {
    "id": "za-gq-co-za",
    "title": "gq.co.za",
    "url": "https://www.gq.co.za/rss/",
    "kind": "news",
    "topic": "world",
    "lean": null,
    "confidence": 0.4,
    "leanRationale": "Discovered via dataset; lean assigned per item by analysis (not source-level).",
    "lang": "nr"
  },
  {
    "id": "za-slikouronlife-co-za",
    "title": "slikouronlife.co.za",
    "url": "https://slikouronlife.co.za/feed/",
    "kind": "news",
    "topic": "world",
    "lean": null,
    "confidence": 0.4,
    "leanRationale": "Discovered via dataset; lean assigned per item by analysis (not source-level).",
    "lang": "nr"
  },
  {
    "id": "za-stuff-co-za",
    "title": "stuff.co.za",
    "url": "https://stuff.co.za/feed/",
    "kind": "news",
    "topic": "world",
    "lean": null,
    "confidence": 0.4,
    "leanRationale": "Discovered via dataset; lean assigned per item by analysis (not source-level).",
    "lang": "nr"
  },
  {
    "id": "za-celebgossip-co-za",
    "title": "celebgossip.co.za",
    "url": "https://www.celebgossip.co.za/feed",
    "kind": "news",
    "topic": "world",
    "lean": null,
    "confidence": 0.4,
    "leanRationale": "Discovered via dataset; lean assigned per item by analysis (not source-level).",
    "lang": "nr"
  },
  {
    "id": "za-lekoafm-co-za",
    "title": "lekoafm.co.za",
    "url": "https://lekoafm.co.za/feed/",
    "kind": "news",
    "topic": "world",
    "lean": null,
    "confidence": 0.4,
    "leanRationale": "Discovered via dataset; lean assigned per item by analysis (not source-level).",
    "lang": "nr"
  },
  {
    "id": "za-radioislam-org-za",
    "title": "radioislam.org.za",
    "url": "https://radioislam.org.za/a/feed/",
    "kind": "news",
    "topic": "world",
    "lean": null,
    "confidence": 0.4,
    "leanRationale": "Discovered via dataset; lean assigned per item by analysis (not source-level).",
    "lang": "nr"
  },
  {
    "id": "za-defenceweb-co-za",
    "title": "defenceweb.co.za",
    "url": "https://defenceweb.co.za/feed/",
    "kind": "news",
    "topic": "world",
    "lean": null,
    "confidence": 0.4,
    "leanRationale": "Discovered via dataset; lean assigned per item by analysis (not source-level).",
    "lang": "nr"
  },
  {
    "id": "za-dievryburger-co-za",
    "title": "dievryburger.co.za",
    "url": "https://www.dievryburger.co.za/feed/",
    "kind": "news",
    "topic": "world",
    "lean": null,
    "confidence": 0.4,
    "leanRationale": "Discovered via dataset; lean assigned per item by analysis (not source-level).",
    "lang": "nr"
  },
  {
    "id": "za-groundup-org-za",
    "title": "groundup.org.za",
    "url": "https://www.groundup.org.za/sitenews/rss/",
    "kind": "news",
    "topic": "world",
    "lean": null,
    "confidence": 0.4,
    "leanRationale": "Discovered via dataset; lean assigned per item by analysis (not source-level).",
    "lang": "nr"
  },
  {
    "id": "za-bloemfonteincourant-co-za",
    "title": "bloemfonteincourant.co.za",
    "url": "https://www.bloemfonteincourant.co.za/feed/",
    "kind": "news",
    "topic": "world",
    "lean": null,
    "confidence": 0.4,
    "leanRationale": "Discovered via dataset; lean assigned per item by analysis (not source-level).",
    "lang": "nr"
  },
  {
    "id": "za-tabloidmedia-co-za",
    "title": "tabloidmedia.co.za",
    "url": "https://tabloidmedia.co.za/feed/",
    "kind": "news",
    "topic": "world",
    "lean": null,
    "confidence": 0.4,
    "leanRationale": "Discovered via dataset; lean assigned per item by analysis (not source-level).",
    "lang": "nr"
  },
  {
    "id": "za-iafrica-com",
    "title": "iafrica.com",
    "url": "https://iafrica.com/feed/",
    "kind": "news",
    "topic": "world",
    "lean": null,
    "confidence": 0.4,
    "leanRationale": "Discovered via dataset; lean assigned per item by analysis (not source-level).",
    "lang": "nr"
  },
  {
    "id": "za-itnewsafrica-com",
    "title": "itnewsafrica.com",
    "url": "https://www.itnewsafrica.com/feed/",
    "kind": "news",
    "topic": "world",
    "lean": null,
    "confidence": 0.4,
    "leanRationale": "Discovered via dataset; lean assigned per item by analysis (not source-level).",
    "lang": "nr"
  },
  {
    "id": "za-cbn-co-za",
    "title": "cbn.co.za",
    "url": "https://cbn.co.za/feed/",
    "kind": "news",
    "topic": "world",
    "lean": null,
    "confidence": 0.4,
    "leanRationale": "Discovered via dataset; lean assigned per item by analysis (not source-level).",
    "lang": "nr"
  },
  {
    "id": "za-capetowner-co-za",
    "title": "capetowner.co.za",
    "url": "https://www.capetowner.co.za/rss/",
    "kind": "news",
    "topic": "world",
    "lean": null,
    "confidence": 0.4,
    "leanRationale": "Discovered via dataset; lean assigned per item by analysis (not source-level).",
    "lang": "nr"
  },
  {
    "id": "za-atlanticsun-co-za",
    "title": "atlanticsun.co.za",
    "url": "https://www.atlanticsun.co.za/rss/",
    "kind": "news",
    "topic": "world",
    "lean": null,
    "confidence": 0.4,
    "leanRationale": "Discovered via dataset; lean assigned per item by analysis (not source-level).",
    "lang": "nr"
  },
  {
    "id": "za-africanminingmarket-com",
    "title": "africanminingmarket.com",
    "url": "https://africanminingmarket.com/feed/",
    "kind": "news",
    "topic": "world",
    "lean": null,
    "confidence": 0.4,
    "leanRationale": "Discovered via dataset; lean assigned per item by analysis (not source-level).",
    "lang": "nr"
  },
  {
    "id": "za-plainsman-co-za",
    "title": "plainsman.co.za",
    "url": "https://www.plainsman.co.za/rss/",
    "kind": "news",
    "topic": "world",
    "lean": null,
    "confidence": 0.4,
    "leanRationale": "Discovered via dataset; lean assigned per item by analysis (not source-level).",
    "lang": "nr"
  },
  {
    "id": "za-politicsweb-co-za",
    "title": "politicsweb.co.za",
    "url": "http://politicsweb.co.za/rss.xml",
    "kind": "news",
    "topic": "world",
    "lean": null,
    "confidence": 0.4,
    "leanRationale": "Discovered via dataset; lean assigned per item by analysis (not source-level).",
    "lang": "nr"
  },
  {
    "id": "za-ilanganews-co-za",
    "title": "ilanganews.co.za",
    "url": "https://ilanganews.co.za/feed/",
    "kind": "news",
    "topic": "world",
    "lean": null,
    "confidence": 0.4,
    "leanRationale": "Discovered via dataset; lean assigned per item by analysis (not source-level).",
    "lang": "nr"
  },
  {
    "id": "za-athlonenews-co-za",
    "title": "athlonenews.co.za",
    "url": "https://www.athlonenews.co.za/rss/",
    "kind": "news",
    "topic": "world",
    "lean": null,
    "confidence": 0.4,
    "leanRationale": "Discovered via dataset; lean assigned per item by analysis (not source-level).",
    "lang": "nr"
  },
  {
    "id": "za-southernmail-co-za",
    "title": "southernmail.co.za",
    "url": "https://www.southernmail.co.za/rss/",
    "kind": "news",
    "topic": "world",
    "lean": null,
    "confidence": 0.4,
    "leanRationale": "Discovered via dataset; lean assigned per item by analysis (not source-level).",
    "lang": "nr"
  },
  {
    "id": "za-northernnews-co-za",
    "title": "northernnews.co.za",
    "url": "https://www.northernnews.co.za/rss/",
    "kind": "news",
    "topic": "world",
    "lean": null,
    "confidence": 0.4,
    "leanRationale": "Discovered via dataset; lean assigned per item by analysis (not source-level).",
    "lang": "nr"
  },
  {
    "id": "za-falsebayecho-co-za",
    "title": "falsebayecho.co.za",
    "url": "https://www.falsebayecho.co.za/rss/",
    "kind": "news",
    "topic": "world",
    "lean": null,
    "confidence": 0.4,
    "leanRationale": "Discovered via dataset; lean assigned per item by analysis (not source-level).",
    "lang": "nr"
  },
  {
    "id": "za-constantiabergbulletin-co-za",
    "title": "constantiabergbulletin.co.za",
    "url": "https://www.constantiabergbulletin.co.za/rss/",
    "kind": "news",
    "topic": "world",
    "lean": null,
    "confidence": 0.4,
    "leanRationale": "Discovered via dataset; lean assigned per item by analysis (not source-level).",
    "lang": "nr"
  },
  {
    "id": "za-techinafrica-com",
    "title": "techinafrica.com",
    "url": "https://www.techinafrica.com/feed/",
    "kind": "news",
    "topic": "world",
    "lean": null,
    "confidence": 0.4,
    "leanRationale": "Discovered via dataset; lean assigned per item by analysis (not source-level).",
    "lang": "nr"
  },
  {
    "id": "za-texxandthecity-com",
    "title": "texxandthecity.com",
    "url": "https://texxandthecity.com/feed/",
    "kind": "news",
    "topic": "world",
    "lean": null,
    "confidence": 0.4,
    "leanRationale": "Discovered via dataset; lean assigned per item by analysis (not source-level).",
    "lang": "nr"
  },
  {
    "id": "za-thegremlin-co-za",
    "title": "thegremlin.co.za",
    "url": "https://www.thegremlin.co.za/feed/",
    "kind": "news",
    "topic": "world",
    "lean": null,
    "confidence": 0.4,
    "leanRationale": "Discovered via dataset; lean assigned per item by analysis (not source-level).",
    "lang": "nr"
  },
  {
    "id": "za-weeklysamirror-news",
    "title": "weeklysamirror.news",
    "url": "https://weeklysamirror.news/feed/",
    "kind": "news",
    "topic": "world",
    "lean": null,
    "confidence": 0.4,
    "leanRationale": "Discovered via dataset; lean assigned per item by analysis (not source-level).",
    "lang": "nr"
  },
  {
    "id": "za-eradiosa-com",
    "title": "eradiosa.com",
    "url": "https://eradiosa.com/feed/",
    "kind": "news",
    "topic": "world",
    "lean": null,
    "confidence": 0.4,
    "leanRationale": "Discovered via dataset; lean assigned per item by analysis (not source-level).",
    "lang": "nr"
  },
  {
    "id": "za-thisisafrica-me",
    "title": "thisisafrica.me",
    "url": "https://thisisafrica.me/feed/",
    "kind": "news",
    "topic": "world",
    "lean": null,
    "confidence": 0.4,
    "leanRationale": "Discovered via dataset; lean assigned per item by analysis (not source-level).",
    "lang": "nr"
  },
  {
    "id": "za-vukaninews-co-za",
    "title": "vukaninews.co.za",
    "url": "https://www.vukaninews.co.za/rss/",
    "kind": "news",
    "topic": "world",
    "lean": null,
    "confidence": 0.4,
    "leanRationale": "Discovered via dataset; lean assigned per item by analysis (not source-level).",
    "lang": "nr"
  },
  {
    "id": "za-goexpress-co-za",
    "title": "goexpress.co.za",
    "url": "https://www.goexpress.co.za/feed/",
    "kind": "news",
    "topic": "world",
    "lean": null,
    "confidence": 0.4,
    "leanRationale": "Discovered via dataset; lean assigned per item by analysis (not source-level).",
    "lang": "nr"
  },
  {
    "id": "za-bolanderlifestyle-co-za",
    "title": "bolanderlifestyle.co.za",
    "url": "https://www.bolanderlifestyle.co.za/rss/",
    "kind": "news",
    "topic": "world",
    "lean": null,
    "confidence": 0.4,
    "leanRationale": "Discovered via dataset; lean assigned per item by analysis (not source-level).",
    "lang": "nr"
  },
  {
    "id": "za-tabletalk-co-za",
    "title": "tabletalk.co.za",
    "url": "https://www.tabletalk.co.za/rss/",
    "kind": "news",
    "topic": "world",
    "lean": null,
    "confidence": 0.4,
    "leanRationale": "Discovered via dataset; lean assigned per item by analysis (not source-level).",
    "lang": "nr"
  },
  {
    "id": "za-mambaonline-com",
    "title": "mambaonline.com",
    "url": "https://www.mambaonline.com/feed/",
    "kind": "news",
    "topic": "world",
    "lean": null,
    "confidence": 0.4,
    "leanRationale": "Discovered via dataset; lean assigned per item by analysis (not source-level).",
    "lang": "nr"
  },
  {
    "id": "za-thenewspaper-co-za",
    "title": "thenewspaper.co.za",
    "url": "https://thenewspaper.co.za/feed/",
    "kind": "news",
    "topic": "world",
    "lean": null,
    "confidence": 0.4,
    "leanRationale": "Discovered via dataset; lean assigned per item by analysis (not source-level).",
    "lang": "nr"
  },
  {
    "id": "za-nismedia-co-za",
    "title": "nismedia.co.za",
    "url": "https://nismedia.co.za/feed/",
    "kind": "news",
    "topic": "world",
    "lean": null,
    "confidence": 0.4,
    "leanRationale": "Discovered via dataset; lean assigned per item by analysis (not source-level).",
    "lang": "nr"
  },
  {
    "id": "za-salaamedia-com",
    "title": "salaamedia.com",
    "url": "https://salaamedia.com/feed/",
    "kind": "news",
    "topic": "world",
    "lean": null,
    "confidence": 0.4,
    "leanRationale": "Discovered via dataset; lean assigned per item by analysis (not source-level).",
    "lang": "nr"
  },
  {
    "id": "za-africanretail-com",
    "title": "africanretail.com",
    "url": "https://www.africanretail.com/feed/",
    "kind": "news",
    "topic": "world",
    "lean": null,
    "confidence": 0.4,
    "leanRationale": "Discovered via dataset; lean assigned per item by analysis (not source-level).",
    "lang": "nr"
  },
  {
    "id": "za-runridedive-com",
    "title": "runridedive.com",
    "url": "https://www.runridedive.com/index.php/feed/",
    "kind": "news",
    "topic": "world",
    "lean": null,
    "confidence": 0.4,
    "leanRationale": "Discovered via dataset; lean assigned per item by analysis (not source-level).",
    "lang": "nr"
  },
  {
    "id": "za-diecourant-co-za",
    "title": "diecourant.co.za",
    "url": "https://diecourant.co.za/feed/",
    "kind": "news",
    "topic": "world",
    "lean": null,
    "confidence": 0.4,
    "leanRationale": "Discovered via dataset; lean assigned per item by analysis (not source-level).",
    "lang": "nr"
  },
  {
    "id": "za-linkfm-co-za",
    "title": "linkfm.co.za",
    "url": "https://linkfm.co.za/feed/",
    "kind": "news",
    "topic": "world",
    "lean": null,
    "confidence": 0.4,
    "leanRationale": "Discovered via dataset; lean assigned per item by analysis (not source-level).",
    "lang": "nr"
  },
  {
    "id": "za-esportscentral-co-za",
    "title": "esportscentral.co.za",
    "url": "https://esportscentral.co.za/feed/",
    "kind": "news",
    "topic": "world",
    "lean": null,
    "confidence": 0.4,
    "leanRationale": "Discovered via dataset; lean assigned per item by analysis (not source-level).",
    "lang": "nr"
  },
  {
    "id": "za-eyethunews-co-za",
    "title": "eyethunews.co.za",
    "url": "https://eyethunews.co.za/feed",
    "kind": "news",
    "topic": "world",
    "lean": null,
    "confidence": 0.4,
    "leanRationale": "Discovered via dataset; lean assigned per item by analysis (not source-level).",
    "lang": "nr"
  },
  {
    "id": "za-courier-net-au",
    "title": "courier.net.au",
    "url": "https://www.courier.net.au/rss/",
    "kind": "news",
    "topic": "world",
    "lean": null,
    "confidence": 0.4,
    "leanRationale": "Discovered via dataset; lean assigned per item by analysis (not source-level).",
    "lang": "nr"
  },
  {
    "id": "za-sentinelnews-co-za",
    "title": "sentinelnews.co.za",
    "url": "https://www.sentinelnews.co.za/rss/",
    "kind": "news",
    "topic": "world",
    "lean": null,
    "confidence": 0.4,
    "leanRationale": "Discovered via dataset; lean assigned per item by analysis (not source-level).",
    "lang": "nr"
  },
  {
    "id": "za-impactradio-co-za",
    "title": "impactradio.co.za",
    "url": "https://impactradio.co.za/feed/",
    "kind": "news",
    "topic": "world",
    "lean": null,
    "confidence": 0.4,
    "leanRationale": "Discovered via dataset; lean assigned per item by analysis (not source-level).",
    "lang": "nr"
  },
  {
    "id": "za-therep-co-za",
    "title": "therep.co.za",
    "url": "https://www.therep.co.za/feed/",
    "kind": "news",
    "topic": "world",
    "lean": null,
    "confidence": 0.4,
    "leanRationale": "Discovered via dataset; lean assigned per item by analysis (not source-level).",
    "lang": "nr"
  },
  {
    "id": "za-health-e-org-za",
    "title": "health-e.org.za",
    "url": "https://health-e.org.za/feed/",
    "kind": "news",
    "topic": "world",
    "lean": null,
    "confidence": 0.4,
    "leanRationale": "Discovered via dataset; lean assigned per item by analysis (not source-level).",
    "lang": "nr"
  },
  {
    "id": "za-kruger2canyon-co-za",
    "title": "kruger2canyon.co.za",
    "url": "https://kruger2canyon.co.za/feed/",
    "kind": "news",
    "topic": "world",
    "lean": null,
    "confidence": 0.4,
    "leanRationale": "Discovered via dataset; lean assigned per item by analysis (not source-level).",
    "lang": "nr"
  },
  {
    "id": "za-diematie-com",
    "title": "diematie.com",
    "url": "https://diematie.com/feed/",
    "kind": "news",
    "topic": "world",
    "lean": null,
    "confidence": 0.4,
    "leanRationale": "Discovered via dataset; lean assigned per item by analysis (not source-level).",
    "lang": "nr"
  },
  {
    "id": "za-edgenews-co-za",
    "title": "edgenews.co.za",
    "url": "https://www.edgenews.co.za/feed/",
    "kind": "news",
    "topic": "world",
    "lean": null,
    "confidence": 0.4,
    "leanRationale": "Discovered via dataset; lean assigned per item by analysis (not source-level).",
    "lang": "nr"
  },
  {
    "id": "za-104fm-co-za",
    "title": "104fm.co.za",
    "url": "https://www.104fm.co.za/feed/",
    "kind": "news",
    "topic": "world",
    "lean": null,
    "confidence": 0.4,
    "leanRationale": "Discovered via dataset; lean assigned per item by analysis (not source-level).",
    "lang": "nr"
  },
  {
    "id": "za-gagasiworld-co-za",
    "title": "gagasiworld.co.za",
    "url": "https://gagasiworld.co.za/feed/",
    "kind": "news",
    "topic": "world",
    "lean": null,
    "confidence": 0.4,
    "leanRationale": "Discovered via dataset; lean assigned per item by analysis (not source-level).",
    "lang": "nr"
  },
  {
    "id": "za-talkofthetown-co-za",
    "title": "talkofthetown.co.za",
    "url": "https://www.talkofthetown.co.za/feed/",
    "kind": "news",
    "topic": "world",
    "lean": null,
    "confidence": 0.4,
    "leanRationale": "Discovered via dataset; lean assigned per item by analysis (not source-level).",
    "lang": "nr"
  },
  {
    "id": "za-spotlightnsp-co-za",
    "title": "spotlightnsp.co.za",
    "url": "https://www.spotlightnsp.co.za/feed/podcast",
    "kind": "news",
    "topic": "world",
    "lean": null,
    "confidence": 0.4,
    "leanRationale": "Discovered via dataset; lean assigned per item by analysis (not source-level).",
    "lang": "nr"
  },
  {
    "id": "za-undergroundpress-co-za",
    "title": "undergroundpress.co.za",
    "url": "https://www.undergroundpress.co.za/?format=feed&amp;type=rss",
    "kind": "news",
    "topic": "world",
    "lean": null,
    "confidence": 0.4,
    "leanRationale": "Discovered via dataset; lean assigned per item by analysis (not source-level).",
    "lang": "nr"
  },
  {
    "id": "za-thisability-co-za",
    "title": "thisability.co.za",
    "url": "https://www.thisability.co.za/feed/",
    "kind": "news",
    "topic": "world",
    "lean": null,
    "confidence": 0.4,
    "leanRationale": "Discovered via dataset; lean assigned per item by analysis (not source-level).",
    "lang": "nr"
  },
  {
    "id": "za-risefm-co-za",
    "title": "risefm.co.za",
    "url": "https://risefm.co.za/feed/",
    "kind": "news",
    "topic": "world",
    "lean": null,
    "confidence": 0.4,
    "leanRationale": "Discovered via dataset; lean assigned per item by analysis (not source-level).",
    "lang": "nr"
  },
  {
    "id": "za-sabc-co-za",
    "title": "sabc.co.za",
    "url": "http://www.sabc.co.za/?feed=rss2",
    "kind": "news",
    "topic": "world",
    "lean": null,
    "confidence": 0.4,
    "leanRationale": "Discovered via dataset; lean assigned per item by analysis (not source-level).",
    "lang": "nr"
  },
  {
    "id": "za-franschhoektatler-co-za",
    "title": "franschhoektatler.co.za",
    "url": "https://www.franschhoektatler.co.za/feed",
    "kind": "news",
    "topic": "world",
    "lean": null,
    "confidence": 0.4,
    "leanRationale": "Discovered via dataset; lean assigned per item by analysis (not source-level).",
    "lang": "nr"
  },
  {
    "id": "za-earthtouchnews-com",
    "title": "earthtouchnews.com",
    "url": "https://www.earthtouchnews.com/feed",
    "kind": "news",
    "topic": "world",
    "lean": null,
    "confidence": 0.4,
    "leanRationale": "Discovered via dataset; lean assigned per item by analysis (not source-level).",
    "lang": "nr"
  },
  {
    "id": "za-iafrikan-com",
    "title": "iafrikan.com",
    "url": "https://iafrikan.com/rss/",
    "kind": "news",
    "topic": "world",
    "lean": null,
    "confidence": 0.4,
    "leanRationale": "Discovered via dataset; lean assigned per item by analysis (not source-level).",
    "lang": "nr"
  },
  {
    "id": "za-thebulletin-co-za",
    "title": "thebulletin.co.za",
    "url": "https://thebulletin.co.za/feed/",
    "kind": "news",
    "topic": "world",
    "lean": null,
    "confidence": 0.4,
    "leanRationale": "Discovered via dataset; lean assigned per item by analysis (not source-level).",
    "lang": "nr"
  },
  {
    "id": "za-journalism-co-za",
    "title": "journalism.co.za",
    "url": "https://journalism.co.za/feed/",
    "kind": "news",
    "topic": "world",
    "lean": null,
    "confidence": 0.4,
    "leanRationale": "Discovered via dataset; lean assigned per item by analysis (not source-level).",
    "lang": "nr"
  },
  {
    "id": "za-witsvuvuzela-com",
    "title": "witsvuvuzela.com",
    "url": "https://witsvuvuzela.com/feed/",
    "kind": "news",
    "topic": "world",
    "lean": null,
    "confidence": 0.4,
    "leanRationale": "Discovered via dataset; lean assigned per item by analysis (not source-level).",
    "lang": "nr"
  },
  {
    "id": "za-stfrancischronicle-com",
    "title": "stfrancischronicle.com",
    "url": "https://stfrancischronicle.com/feed/",
    "kind": "news",
    "topic": "world",
    "lean": null,
    "confidence": 0.4,
    "leanRationale": "Discovered via dataset; lean assigned per item by analysis (not source-level).",
    "lang": "nr"
  },
  {
    "id": "za-amabhungane-org",
    "title": "amabhungane.org",
    "url": "https://amabhungane.org/feed/",
    "kind": "news",
    "topic": "world",
    "lean": null,
    "confidence": 0.4,
    "leanRationale": "Discovered via dataset; lean assigned per item by analysis (not source-level).",
    "lang": "nr"
  },
  {
    "id": "za-forbesafrica-com",
    "title": "forbesafrica.com",
    "url": "http://forbesafrica.com/feed.xml",
    "kind": "news",
    "topic": "world",
    "lean": null,
    "confidence": 0.4,
    "leanRationale": "Discovered via dataset; lean assigned per item by analysis (not source-level).",
    "lang": "nr"
  },
  {
    "id": "za-africabusinessradio-com",
    "title": "africabusinessradio.com",
    "url": "https://africabusinessradio.com/feed/",
    "kind": "news",
    "topic": "world",
    "lean": null,
    "confidence": 0.4,
    "leanRationale": "Discovered via dataset; lean assigned per item by analysis (not source-level).",
    "lang": "nr"
  },
  {
    "id": "za-vryeweekblad-com",
    "title": "vryeweekblad.com",
    "url": "https://www.vryeweekblad.com/rss",
    "kind": "news",
    "topic": "world",
    "lean": null,
    "confidence": 0.4,
    "leanRationale": "Discovered via dataset; lean assigned per item by analysis (not source-level).",
    "lang": "nr"
  },
  {
    "id": "za-derebus-org-za",
    "title": "derebus.org.za",
    "url": "https://www.derebus.org.za/feed/",
    "kind": "news",
    "topic": "world",
    "lean": null,
    "confidence": 0.4,
    "leanRationale": "Discovered via dataset; lean assigned per item by analysis (not source-level).",
    "lang": "nr"
  },
  {
    "id": "za-capitalnewspapers-co-za",
    "title": "capitalnewspapers.co.za",
    "url": "https://capitalnewspapers.co.za/feed",
    "kind": "news",
    "topic": "world",
    "lean": null,
    "confidence": 0.4,
    "leanRationale": "Discovered via dataset; lean assigned per item by analysis (not source-level).",
    "lang": "nr"
  },
  {
    "id": "za-midsouthcoastrisingsun-co-za",
    "title": "midsouthcoastrisingsun.co.za",
    "url": "https://midsouthcoastrisingsun.co.za/feed",
    "kind": "news",
    "topic": "world",
    "lean": null,
    "confidence": 0.4,
    "leanRationale": "Discovered via dataset; lean assigned per item by analysis (not source-level).",
    "lang": "nr"
  },
  {
    "id": "za-find-it-co-za",
    "title": "find-it.co.za",
    "url": "https://nuusflits.com/feed/",
    "kind": "news",
    "topic": "world",
    "lean": null,
    "confidence": 0.4,
    "leanRationale": "Discovered via dataset; lean assigned per item by analysis (not source-level).",
    "lang": "nr"
  },
  {
    "id": "za-radioveritas-co-za",
    "title": "radioveritas.co.za",
    "url": "https://radioveritas.co.za/feed/",
    "kind": "news",
    "topic": "world",
    "lean": null,
    "confidence": 0.4,
    "leanRationale": "Discovered via dataset; lean assigned per item by analysis (not source-level).",
    "lang": "nr"
  },
  {
    "id": "za-ssnewsnow-com",
    "title": "ssnewsnow.com",
    "url": "https://ssnewsnow.com/feed",
    "kind": "news",
    "topic": "world",
    "lean": null,
    "confidence": 0.4,
    "leanRationale": "Discovered via dataset; lean assigned per item by analysis (not source-level).",
    "lang": "nr"
  },
  {
    "id": "za-theballitomagazine-co-za",
    "title": "theballitomagazine.co.za",
    "url": "https://www.theballitomagazine.co.za/feed.xml",
    "kind": "news",
    "topic": "world",
    "lean": null,
    "confidence": 0.4,
    "leanRationale": "Discovered via dataset; lean assigned per item by analysis (not source-level).",
    "lang": "nr"
  },
  {
    "id": "za-diepos-co-za",
    "title": "diepos.co.za",
    "url": "https://diepos.co.za/feed",
    "kind": "news",
    "topic": "world",
    "lean": null,
    "confidence": 0.4,
    "leanRationale": "Discovered via dataset; lean assigned per item by analysis (not source-level).",
    "lang": "nr"
  },
  {
    "id": "za-goodnewsdaily-co-za",
    "title": "goodnewsdaily.co.za",
    "url": "https://goodnewsdaily.co.za/feed",
    "kind": "news",
    "topic": "world",
    "lean": null,
    "confidence": 0.4,
    "leanRationale": "Discovered via dataset; lean assigned per item by analysis (not source-level).",
    "lang": "nr"
  },
  {
    "id": "za-thepinktongue-co-za",
    "title": "thepinktongue.co.za",
    "url": "https://www.thepinktongue.co.za/feed/",
    "kind": "news",
    "topic": "world",
    "lean": null,
    "confidence": 0.4,
    "leanRationale": "Discovered via dataset; lean assigned per item by analysis (not source-level).",
    "lang": "nr"
  },
  {
    "id": "za-capricornfm-co-za",
    "title": "capricornfm.co.za",
    "url": "https://www.capricornfm.co.za/feed/",
    "kind": "news",
    "topic": "world",
    "lean": null,
    "confidence": 0.4,
    "leanRationale": "Discovered via dataset; lean assigned per item by analysis (not source-level).",
    "lang": "nr"
  },
  {
    "id": "za-propertywheel-co-za",
    "title": "propertywheel.co.za",
    "url": "https://propertywheel.co.za/feed/",
    "kind": "news",
    "topic": "world",
    "lean": null,
    "confidence": 0.4,
    "leanRationale": "Discovered via dataset; lean assigned per item by analysis (not source-level).",
    "lang": "nr"
  },
  {
    "id": "za-noseweek-co-za",
    "title": "noseweek.co.za",
    "url": "https://noseweek.co.za/wp/feed/",
    "kind": "news",
    "topic": "world",
    "lean": null,
    "confidence": 0.4,
    "leanRationale": "Discovered via dataset; lean assigned per item by analysis (not source-level).",
    "lang": "nr"
  },
  {
    "id": "za-grocotts-co-za",
    "title": "grocotts.co.za",
    "url": "http://grocotts.co.za/feed",
    "kind": "news",
    "topic": "world",
    "lean": null,
    "confidence": 0.4,
    "leanRationale": "Discovered via dataset; lean assigned per item by analysis (not source-level).",
    "lang": "nr"
  },
  {
    "id": "za-moneyweb-co-za",
    "title": "moneyweb.co.za",
    "url": "https://www.moneyweb.co.za/feed",
    "kind": "news",
    "topic": "world",
    "lean": null,
    "confidence": 0.4,
    "leanRationale": "Discovered via dataset; lean assigned per item by analysis (not source-level).",
    "lang": "nr"
  },
  {
    "id": "za-sajr-co-za",
    "title": "sajr.co.za",
    "url": "https://www.sajr.co.za/feed/",
    "kind": "news",
    "topic": "world",
    "lean": null,
    "confidence": 0.4,
    "leanRationale": "Discovered via dataset; lean assigned per item by analysis (not source-level).",
    "lang": "nr"
  },
  {
    "id": "za-ekurhuleninews-co-za",
    "title": "ekurhuleninews.co.za",
    "url": "https://ekurhuleninews.co.za/feed/",
    "kind": "news",
    "topic": "world",
    "lean": null,
    "confidence": 0.4,
    "leanRationale": "Discovered via dataset; lean assigned per item by analysis (not source-level).",
    "lang": "nr"
  },
  {
    "id": "za-bhekisisa-org",
    "title": "bhekisisa.org",
    "url": "https://bhekisisa.org/feed/",
    "kind": "news",
    "topic": "world",
    "lean": null,
    "confidence": 0.4,
    "leanRationale": "Discovered via dataset; lean assigned per item by analysis (not source-level).",
    "lang": "nr"
  },
  {
    "id": "za-africantechroundup-com",
    "title": "africantechroundup.com",
    "url": "https://www.africantechroundup.com/rss/",
    "kind": "news",
    "topic": "world",
    "lean": null,
    "confidence": 0.4,
    "leanRationale": "Discovered via dataset; lean assigned per item by analysis (not source-level).",
    "lang": "nr"
  },
  {
    "id": "za-ciiradio-com",
    "title": "ciiradio.com",
    "url": "https://ciiradio.com/feed",
    "kind": "news",
    "topic": "world",
    "lean": null,
    "confidence": 0.4,
    "leanRationale": "Discovered via dataset; lean assigned per item by analysis (not source-level).",
    "lang": "nr"
  },
  {
    "id": "za-risingsunchatsworth-co-za",
    "title": "risingsunchatsworth.co.za",
    "url": "http://risingsunchatsworth.co.za/feed",
    "kind": "news",
    "topic": "world",
    "lean": null,
    "confidence": 0.4,
    "leanRationale": "Discovered via dataset; lean assigned per item by analysis (not source-level).",
    "lang": "nr"
  },
  {
    "id": "za-capetownmagazine-com",
    "title": "capetownmagazine.com",
    "url": "https://www.capetownmagazine.com/rss",
    "kind": "news",
    "topic": "world",
    "lean": null,
    "confidence": 0.4,
    "leanRationale": "Discovered via dataset; lean assigned per item by analysis (not source-level).",
    "lang": "nr"
  },
  {
    "id": "za-theannouncer-co-za",
    "title": "theannouncer.co.za",
    "url": "https://theannouncer.co.za/feed",
    "kind": "news",
    "topic": "world",
    "lean": null,
    "confidence": 0.4,
    "leanRationale": "Discovered via dataset; lean assigned per item by analysis (not source-level).",
    "lang": "nr"
  },
  {
    "id": "za-risingsunlenasia-co-za",
    "title": "risingsunlenasia.co.za",
    "url": "http://www.risingsunlenasia.co.za/feed",
    "kind": "news",
    "topic": "world",
    "lean": null,
    "confidence": 0.4,
    "leanRationale": "Discovered via dataset; lean assigned per item by analysis (not source-level).",
    "lang": "nr"
  },
  {
    "id": "za-kwevoel-co-za",
    "title": "kwevoel.co.za",
    "url": "https://www.kwevoel.co.za/feed/",
    "kind": "news",
    "topic": "world",
    "lean": null,
    "confidence": 0.4,
    "leanRationale": "Discovered via dataset; lean assigned per item by analysis (not source-level).",
    "lang": "nr"
  },
  {
    "id": "za-kormorant-co-za",
    "title": "kormorant.co.za",
    "url": "https://kormorant.co.za/feed/",
    "kind": "news",
    "topic": "world",
    "lean": null,
    "confidence": 0.4,
    "leanRationale": "Discovered via dataset; lean assigned per item by analysis (not source-level).",
    "lang": "nr"
  },
  {
    "id": "za-pretoriafm-co-za",
    "title": "pretoriafm.co.za",
    "url": "https://www.pretoriafm.co.za/feed/",
    "kind": "news",
    "topic": "world",
    "lean": null,
    "confidence": 0.4,
    "leanRationale": "Discovered via dataset; lean assigned per item by analysis (not source-level).",
    "lang": "nr"
  },
  {
    "id": "za-vulankungu-co-za",
    "title": "vulankungu.co.za",
    "url": "https://vulankungu.co.za/rss.xml",
    "kind": "news",
    "topic": "world",
    "lean": null,
    "confidence": 0.4,
    "leanRationale": "Discovered via dataset; lean assigned per item by analysis (not source-level).",
    "lang": "nr"
  },
  {
    "id": "za-northwestnewspapers-co-za",
    "title": "northwestnewspapers.co.za",
    "url": "https://www.northwestnewspapers.co.za/gemsbok/?format=feed&amp;type=rss",
    "kind": "news",
    "topic": "world",
    "lean": null,
    "confidence": 0.4,
    "leanRationale": "Discovered via dataset; lean assigned per item by analysis (not source-level).",
    "lang": "nr"
  },
  {
    "id": "za-thepost-org-za",
    "title": "thepost.org.za",
    "url": "https://thepost.org.za/feed/",
    "kind": "news",
    "topic": "world",
    "lean": null,
    "confidence": 0.4,
    "leanRationale": "Discovered via dataset; lean assigned per item by analysis (not source-level).",
    "lang": "nr"
  },
  {
    "id": "za-pdby-co-za",
    "title": "pdby.co.za",
    "url": "https://pdby.co.za/feed/",
    "kind": "news",
    "topic": "world",
    "lean": null,
    "confidence": 0.4,
    "leanRationale": "Discovered via dataset; lean assigned per item by analysis (not source-level).",
    "lang": "nr"
  },
  {
    "id": "za-markazsahaba-com",
    "title": "markazsahaba.com",
    "url": "https://markazsahaba.com/feed",
    "kind": "news",
    "topic": "world",
    "lean": null,
    "confidence": 0.4,
    "leanRationale": "Discovered via dataset; lean assigned per item by analysis (not source-level).",
    "lang": "nr"
  },
  {
    "id": "za-alive2green-co-za",
    "title": "alive2green.co.za",
    "url": "https://sustainability-handbook.alive2green.co.za/?feed=rss2",
    "kind": "news",
    "topic": "world",
    "lean": null,
    "confidence": 0.4,
    "leanRationale": "Discovered via dataset; lean assigned per item by analysis (not source-level).",
    "lang": "nr"
  },
  {
    "id": "za-radiohoutstok-fm",
    "title": "radiohoutstok.fm",
    "url": "https://radiohoutstok.fm/feed/",
    "kind": "news",
    "topic": "world",
    "lean": null,
    "confidence": 0.4,
    "leanRationale": "Discovered via dataset; lean assigned per item by analysis (not source-level).",
    "lang": "nr"
  },
  {
    "id": "za-mbhashefm-co-za",
    "title": "mbhashefm.co.za",
    "url": "https://mbhashefm.co.za/feed/",
    "kind": "news",
    "topic": "world",
    "lean": null,
    "confidence": 0.4,
    "leanRationale": "Discovered via dataset; lean assigned per item by analysis (not source-level).",
    "lang": "nr"
  },
  {
    "id": "za-934fm-co-za",
    "title": "934fm.co.za",
    "url": "https://www.934fm.co.za/feed",
    "kind": "news",
    "topic": "world",
    "lean": null,
    "confidence": 0.4,
    "leanRationale": "Discovered via dataset; lean assigned per item by analysis (not source-level).",
    "lang": "nr"
  },
  {
    "id": "za-falcons-org-za",
    "title": "falcons.org.za",
    "url": "https://falcons.org.za/feed/",
    "kind": "news",
    "topic": "world",
    "lean": null,
    "confidence": 0.4,
    "leanRationale": "Discovered via dataset; lean assigned per item by analysis (not source-level).",
    "lang": "nr"
  },
  {
    "id": "za-onskontrei-co-za",
    "title": "onskontrei.co.za",
    "url": "https://onskontrei.co.za/feed/",
    "kind": "news",
    "topic": "world",
    "lean": null,
    "confidence": 0.4,
    "leanRationale": "Discovered via dataset; lean assigned per item by analysis (not source-level).",
    "lang": "nr"
  },
  {
    "id": "za-mountainecho-co-za",
    "title": "mountainecho.co.za",
    "url": "http://www.mountainecho.co.za/index.php?format=feed&amp;type=rss",
    "kind": "news",
    "topic": "world",
    "lean": null,
    "confidence": 0.4,
    "leanRationale": "Discovered via dataset; lean assigned per item by analysis (not source-level).",
    "lang": "nr"
  },
  {
    "id": "za-westvilletimes-co-za",
    "title": "westvilletimes.co.za",
    "url": "https://westvilletimes.co.za/feed/",
    "kind": "news",
    "topic": "world",
    "lean": null,
    "confidence": 0.4,
    "leanRationale": "Discovered via dataset; lean assigned per item by analysis (not source-level).",
    "lang": "nr"
  },
  {
    "id": "za-ziwaphi-com",
    "title": "ziwaphi.com",
    "url": "https://www.ziwaphi.com/feed/",
    "kind": "news",
    "topic": "world",
    "lean": null,
    "confidence": 0.4,
    "leanRationale": "Discovered via dataset; lean assigned per item by analysis (not source-level).",
    "lang": "nr"
  },
  {
    "id": "za-ncnn-live",
    "title": "ncnn.live",
    "url": "https://ncnn.live/feed/",
    "kind": "news",
    "topic": "world",
    "lean": null,
    "confidence": 0.4,
    "leanRationale": "Discovered via dataset; lean assigned per item by analysis (not source-level).",
    "lang": "nr"
  },
  {
    "id": "za-hindvani-co-za",
    "title": "hindvani.co.za",
    "url": "https://hindvani.co.za/feed/",
    "kind": "news",
    "topic": "world",
    "lean": null,
    "confidence": 0.4,
    "leanRationale": "Discovered via dataset; lean assigned per item by analysis (not source-level).",
    "lang": "nr"
  },
  {
    "id": "za-ccfm-org-za",
    "title": "ccfm.org.za",
    "url": "https://www.ccfm.org.za/feed/",
    "kind": "news",
    "topic": "world",
    "lean": null,
    "confidence": 0.4,
    "leanRationale": "Discovered via dataset; lean assigned per item by analysis (not source-level).",
    "lang": "nr"
  },
  {
    "id": "za-kasiefm971-co-za",
    "title": "kasiefm971.co.za",
    "url": "https://kasiefm971.co.za/feed/",
    "kind": "news",
    "topic": "world",
    "lean": null,
    "confidence": 0.4,
    "leanRationale": "Discovered via dataset; lean assigned per item by analysis (not source-level).",
    "lang": "nr"
  },
  {
    "id": "za-ubunturadio-com",
    "title": "ubunturadio.com",
    "url": "https://ubunturadio.com/feed/",
    "kind": "news",
    "topic": "world",
    "lean": null,
    "confidence": 0.4,
    "leanRationale": "Discovered via dataset; lean assigned per item by analysis (not source-level).",
    "lang": "nr"
  },
  {
    "id": "za-nationradio-co-za",
    "title": "nationradio.co.za",
    "url": "https://nationradio.co.za/feed/",
    "kind": "news",
    "topic": "world",
    "lean": null,
    "confidence": 0.4,
    "leanRationale": "Discovered via dataset; lean assigned per item by analysis (not source-level).",
    "lang": "nr"
  },
  {
    "id": "za-cityradio-co-za",
    "title": "cityradio.co.za",
    "url": "https://cityradio.co.za/feed/",
    "kind": "news",
    "topic": "world",
    "lean": null,
    "confidence": 0.4,
    "leanRationale": "Discovered via dataset; lean assigned per item by analysis (not source-level).",
    "lang": "nr"
  },
  {
    "id": "za-discoverlimpopomag-co-za",
    "title": "discoverlimpopomag.co.za",
    "url": "https://www.discoverlimpopomag.co.za/feed/",
    "kind": "news",
    "topic": "world",
    "lean": null,
    "confidence": 0.4,
    "leanRationale": "Discovered via dataset; lean assigned per item by analysis (not source-level).",
    "lang": "nr"
  },
  {
    "id": "za-thefreestater-co-za",
    "title": "thefreestater.co.za",
    "url": "http://thefreestater.co.za/feed/",
    "kind": "news",
    "topic": "world",
    "lean": null,
    "confidence": 0.4,
    "leanRationale": "Discovered via dataset; lean assigned per item by analysis (not source-level).",
    "lang": "nr"
  },
  {
    "id": "za-africanxmag-com",
    "title": "africanxmag.com",
    "url": "https://africanxmag.com/feed/",
    "kind": "news",
    "topic": "world",
    "lean": null,
    "confidence": 0.4,
    "leanRationale": "Discovered via dataset; lean assigned per item by analysis (not source-level).",
    "lang": "nr"
  },
  {
    "id": "za-kougaexpress-co-za",
    "title": "kougaexpress.co.za",
    "url": "https://novanews.co.za/kougaexpress/feed/",
    "kind": "news",
    "topic": "world",
    "lean": null,
    "confidence": 0.4,
    "leanRationale": "Discovered via dataset; lean assigned per item by analysis (not source-level).",
    "lang": "nr"
  },
  {
    "id": "za-news-co-za",
    "title": "news.co.za",
    "url": "https://news.co.za/feed",
    "kind": "news",
    "topic": "world",
    "lean": null,
    "confidence": 0.4,
    "leanRationale": "Discovered via dataset; lean assigned per item by analysis (not source-level).",
    "lang": "nr"
  },
  {
    "id": "za-bitounews-co-za",
    "title": "bitounews.co.za",
    "url": "http://bitounews.co.za/?feed=rss2",
    "kind": "news",
    "topic": "world",
    "lean": null,
    "confidence": 0.4,
    "leanRationale": "Discovered via dataset; lean assigned per item by analysis (not source-level).",
    "lang": "nr"
  },
  {
    "id": "za-sleekfm-com",
    "title": "sleekfm.com",
    "url": "https://www.sleekfm.com/feed",
    "kind": "news",
    "topic": "world",
    "lean": null,
    "confidence": 0.4,
    "leanRationale": "Discovered via dataset; lean assigned per item by analysis (not source-level).",
    "lang": "nr"
  },
  {
    "id": "za-newsnote-co-za",
    "title": "newsnote.co.za",
    "url": "https://newsnote.co.za/feed/",
    "kind": "news",
    "topic": "world",
    "lean": null,
    "confidence": 0.4,
    "leanRationale": "Discovered via dataset; lean assigned per item by analysis (not source-level).",
    "lang": "nr"
  },
  {
    "id": "za-weslander-co-za",
    "title": "weslander.co.za",
    "url": "https://novanews.co.za/weslander/feed/",
    "kind": "news",
    "topic": "world",
    "lean": null,
    "confidence": 0.4,
    "leanRationale": "Discovered via dataset; lean assigned per item by analysis (not source-level).",
    "lang": "nr"
  },
  {
    "id": "za-eikestadnuus-co-za",
    "title": "eikestadnuus.co.za",
    "url": "https://novanews.co.za/eikestadnuus/feed/",
    "kind": "news",
    "topic": "world",
    "lean": null,
    "confidence": 0.4,
    "leanRationale": "Discovered via dataset; lean assigned per item by analysis (not source-level).",
    "lang": "nr"
  },
  {
    "id": "za-paarlpost-co-za",
    "title": "paarlpost.co.za",
    "url": "https://novanews.co.za/paarlpost/feed/",
    "kind": "news",
    "topic": "world",
    "lean": null,
    "confidence": 0.4,
    "leanRationale": "Discovered via dataset; lean assigned per item by analysis (not source-level).",
    "lang": "nr"
  },
  {
    "id": "za-hermanustimes-co-za",
    "title": "hermanustimes.co.za",
    "url": "https://novanews.co.za/hermanustimes/feed/",
    "kind": "news",
    "topic": "world",
    "lean": null,
    "confidence": 0.4,
    "leanRationale": "Discovered via dataset; lean assigned per item by analysis (not source-level).",
    "lang": "nr"
  },
  {
    "id": "za-franschhoeklife-co-za",
    "title": "franschhoeklife.co.za",
    "url": "https://lifebrands.co.za/feed",
    "kind": "news",
    "topic": "world",
    "lean": null,
    "confidence": 0.4,
    "leanRationale": "Discovered via dataset; lean assigned per item by analysis (not source-level).",
    "lang": "nr"
  },
  {
    "id": "za-peoplespost-co-za",
    "title": "peoplespost.co.za",
    "url": "https://novanews.co.za/peoplespost/feed/",
    "kind": "news",
    "topic": "world",
    "lean": null,
    "confidence": 0.4,
    "leanRationale": "Discovered via dataset; lean assigned per item by analysis (not source-level).",
    "lang": "nr"
  },
  {
    "id": "za-tygerburger-co-za",
    "title": "tygerburger.co.za",
    "url": "https://novanews.co.za/tygerburger/feed/",
    "kind": "news",
    "topic": "world",
    "lean": null,
    "confidence": 0.4,
    "leanRationale": "Discovered via dataset; lean assigned per item by analysis (not source-level).",
    "lang": "nr"
  },
  {
    "id": "za-ud-news-co-za",
    "title": "ud-news.co.za",
    "url": "https://novanews.co.za/udexpress/feed/",
    "kind": "news",
    "topic": "world",
    "lean": null,
    "confidence": 0.4,
    "leanRationale": "Discovered via dataset; lean assigned per item by analysis (not source-level).",
    "lang": "nr"
  },
  {
    "id": "za-pe-express-co-za",
    "title": "pe-express.co.za",
    "url": "https://novanews.co.za/peexpress/feed/",
    "kind": "news",
    "topic": "world",
    "lean": null,
    "confidence": 0.4,
    "leanRationale": "Discovered via dataset; lean assigned per item by analysis (not source-level).",
    "lang": "nr"
  },
  {
    "id": "za-theumhlangamagazine-co-za",
    "title": "theumhlangamagazine.co.za",
    "url": "https://www.theumhlangamagazine.co.za/feed.xml",
    "kind": "news",
    "topic": "world",
    "lean": null,
    "confidence": 0.4,
    "leanRationale": "Discovered via dataset; lean assigned per item by analysis (not source-level).",
    "lang": "nr"
  },
  {
    "id": "za-alexfm-co-za",
    "title": "alexfm.co.za",
    "url": "http://www.alexfm.co.za/?feed=rss2",
    "kind": "news",
    "topic": "world",
    "lean": null,
    "confidence": 0.4,
    "leanRationale": "Discovered via dataset; lean assigned per item by analysis (not source-level).",
    "lang": "nr"
  },
  {
    "id": "za-mthathaexpress-co-za",
    "title": "mthathaexpress.co.za",
    "url": "https://novanews.co.za/mthathaexpress/feed/",
    "kind": "news",
    "topic": "world",
    "lean": null,
    "confidence": 0.4,
    "leanRationale": "Discovered via dataset; lean assigned per item by analysis (not source-level).",
    "lang": "nr"
  }
]
